{
  "dataset": {
    "id": "gems-and-jewellery-exports-hs8-non-us-imports-monthly",
    "label": "Monthly HS8 Global Indian exports excluding the US",
    "scope": "non-us-imports",
    "sourceFile": "Derived from global HS8 exports minus US-reported gems and jewellery imports from India",
    "valueLabel": "Export value (US $)",
    "expectedGranularity": "monthly",
    "actualGranularity": "monthly",
    "coverage": {
      "2024": [
        1,
        2,
        3,
        4,
        5,
        6,
        7,
        8,
        9,
        10,
        11,
        12
      ],
      "2025": [
        1,
        2,
        3,
        4,
        5,
        6,
        7,
        8,
        9,
        10,
        11,
        12
      ],
      "2026": [
        1,
        2,
        3
      ]
    },
    "hs2Commodities": [
      {
        "hsCode": "71",
        "name": "71"
      }
    ],
    "periods": [
      {
        "key": "2024-01",
        "label": "Jan 2024",
        "sort": 202401
      },
      {
        "key": "2024-02",
        "label": "Feb 2024",
        "sort": 202402
      },
      {
        "key": "2024-03",
        "label": "Mar 2024",
        "sort": 202403
      },
      {
        "key": "2024-04",
        "label": "Apr 2024",
        "sort": 202404
      },
      {
        "key": "2024-05",
        "label": "May 2024",
        "sort": 202405
      },
      {
        "key": "2024-06",
        "label": "Jun 2024",
        "sort": 202406
      },
      {
        "key": "2024-07",
        "label": "Jul 2024",
        "sort": 202407
      },
      {
        "key": "2024-08",
        "label": "Aug 2024",
        "sort": 202408
      },
      {
        "key": "2024-09",
        "label": "Sep 2024",
        "sort": 202409
      },
      {
        "key": "2024-10",
        "label": "Oct 2024",
        "sort": 202410
      },
      {
        "key": "2024-11",
        "label": "Nov 2024",
        "sort": 202411
      },
      {
        "key": "2024-12",
        "label": "Dec 2024",
        "sort": 202412
      },
      {
        "key": "2025-01",
        "label": "Jan 2025",
        "sort": 202501
      },
      {
        "key": "2025-02",
        "label": "Feb 2025",
        "sort": 202502
      },
      {
        "key": "2025-03",
        "label": "Mar 2025",
        "sort": 202503
      },
      {
        "key": "2025-04",
        "label": "Apr 2025",
        "sort": 202504
      },
      {
        "key": "2025-05",
        "label": "May 2025",
        "sort": 202505
      },
      {
        "key": "2025-06",
        "label": "Jun 2025",
        "sort": 202506
      },
      {
        "key": "2025-07",
        "label": "Jul 2025",
        "sort": 202507
      },
      {
        "key": "2025-08",
        "label": "Aug 2025",
        "sort": 202508
      },
      {
        "key": "2025-09",
        "label": "Sep 2025",
        "sort": 202509
      },
      {
        "key": "2025-10",
        "label": "Oct 2025",
        "sort": 202510
      },
      {
        "key": "2025-11",
        "label": "Nov 2025",
        "sort": 202511
      },
      {
        "key": "2025-12",
        "label": "Dec 2025",
        "sort": 202512
      },
      {
        "key": "2026-01",
        "label": "Jan 2026",
        "sort": 202601
      },
      {
        "key": "2026-02",
        "label": "Feb 2026",
        "sort": 202602
      },
      {
        "key": "2026-03",
        "label": "Mar 2026",
        "sort": 202603
      }
    ],
    "commodities": [
      {
        "id": "hs8_71011030",
        "hsCode": "71",
        "hs4Code": "7101",
        "hs6Code": "710110",
        "hs8Code": "71011030",
        "name": "71011030 Natural Pearls Graded And Temporarily Strung (gm)",
        "total": -81769
      },
      {
        "id": "hs8_71011060",
        "hsCode": "71",
        "hs4Code": "7101",
        "hs6Code": "710110",
        "hs8Code": "71011060",
        "name": "71011060 Natural Pearls, Nesoi (gm)",
        "total": -74539
      },
      {
        "id": "hs8_71012100",
        "hsCode": "71",
        "hs4Code": "7101",
        "hs6Code": "710121",
        "hs8Code": "71012100",
        "name": "71012100 CULTURED PEARLS UNWRKD",
        "total": -260508
      },
      {
        "id": "hs8_71012230",
        "hsCode": "71",
        "hs4Code": "7101",
        "hs6Code": "710122",
        "hs8Code": "71012230",
        "name": "71012230 Cultured Pearls, Worked,graded,temporarily Strung (gm)",
        "total": -110021
      },
      {
        "id": "hs8_71012260",
        "hsCode": "71",
        "hs4Code": "7101",
        "hs6Code": "710122",
        "hs8Code": "71012260",
        "name": "71012260 Cultured Pearls, Worked, Nesoi (gm)",
        "total": -157759
      },
      {
        "id": "hs8_71021000",
        "hsCode": "71",
        "hs4Code": "7102",
        "hs6Code": "710210",
        "hs8Code": "71021000",
        "name": "71021000 UNSORTED DIAMONDS W/N WORKED,NOT MOUNTED",
        "total": -31298
      },
      {
        "id": "hs8_71022110",
        "hsCode": "71",
        "hs4Code": "7102",
        "hs6Code": "710221",
        "hs8Code": "71022110",
        "name": "71022110 SORTED INDUSTRIAL DIAMONDS",
        "total": 9555875
      },
      {
        "id": "hs8_71022130",
        "hsCode": "71",
        "hs4Code": "7102",
        "hs6Code": "710221",
        "hs8Code": "71022130",
        "name": "71022130 Ind Dimnds Smpl Swn Clvd Or Brted Excpt Miners (car)",
        "total": -62113
      },
      {
        "id": "hs8_71022140",
        "hsCode": "71",
        "hs4Code": "7102",
        "hs6Code": "710221",
        "hs8Code": "71022140",
        "name": "71022140 Industrial Diamonds Unworked, Nesoi (car)",
        "total": -229782
      },
      {
        "id": "hs8_71022900",
        "hsCode": "71",
        "hs4Code": "7102",
        "hs6Code": "710229",
        "hs8Code": "71022900",
        "name": "71022900 Industrial Diamonds (miners Carbonados) Worked (car)",
        "total": -717237
      },
      {
        "id": "hs8_71023100",
        "hsCode": "71",
        "hs4Code": "7102",
        "hs6Code": "710231",
        "hs8Code": "71023100",
        "name": "71023100 NON-INDUSTRIAL DIAMONDS UNWORKED/SIMPLY   SAWN CLEAVED OR BRUTED",
        "total": 1141082400
      },
      {
        "id": "hs8_71023900",
        "hsCode": "71",
        "hs4Code": "7102",
        "hs6Code": "710239",
        "hs8Code": "71023900",
        "name": "71023900 Nonindustrial Diamonds Weighing &lt;= 0.5CT Each (car)",
        "total": -10436452840
      },
      {
        "id": "hs8_71031020",
        "hsCode": "71",
        "hs4Code": "7103",
        "hs6Code": "710310",
        "hs8Code": "71031020",
        "name": "71031020 Unworked Precious And Semiprecious Stones (car)",
        "total": -4055123
      },
      {
        "id": "hs8_71031040",
        "hsCode": "71",
        "hs4Code": "7103",
        "hs6Code": "710310",
        "hs8Code": "71031040",
        "name": "71031040 Simply Sawn/roughly Shaped Precious/semipr Stones (car)",
        "total": -464350
      },
      {
        "id": "hs8_71039100",
        "hsCode": "71",
        "hs4Code": "7103",
        "hs6Code": "710391",
        "hs8Code": "71039100",
        "name": "71039100 Rubies Cut But Not Set For Jewelry (car)",
        "total": -314502958
      },
      {
        "id": "hs8_71039910",
        "hsCode": "71",
        "hs4Code": "7103",
        "hs6Code": "710399",
        "hs8Code": "71039910",
        "name": "71039910 Gemstones, Cut But Not Set Suitbl Fr Jewlry, Nesoi (car)",
        "total": -159455185
      },
      {
        "id": "hs8_71039950",
        "hsCode": "71",
        "hs4Code": "7103",
        "hs6Code": "710399",
        "hs8Code": "71039950",
        "name": "71039950 Gemstones, Othrws Wrkd, Nt Suitbl For Jwlry, Nesoi (car)",
        "total": -3813925
      },
      {
        "id": "hs8_71041000",
        "hsCode": "71",
        "hs4Code": "7104",
        "hs6Code": "710410",
        "hs8Code": "71041000",
        "name": "71041000 PIEZO ELECTRIC QUARTZ",
        "total": -130724
      },
      {
        "id": "hs8_71042100",
        "hsCode": "71",
        "hs4Code": "7104",
        "hs6Code": "710421",
        "hs8Code": "71042100",
        "name": "71042100 Synthetic Diamonds, Unworked Or Simply Sawn/rough (gm)",
        "total": -3424537
      },
      {
        "id": "hs8_71042900",
        "hsCode": "71",
        "hs4Code": "7104",
        "hs6Code": "710429",
        "hs8Code": "71042900",
        "name": "71042900 OTHER",
        "total": 1520462
      },
      {
        "id": "hs8_71049110",
        "hsCode": "71",
        "hs4Code": "7104",
        "hs6Code": "710491",
        "hs8Code": "71049110",
        "name": "71049110 Industrial Diamonds",
        "total": -1459195251
      },
      {
        "id": "hs8_71049150",
        "hsCode": "71",
        "hs4Code": "7104",
        "hs6Code": "710491",
        "hs8Code": "71049150",
        "name": "71049150 Syn, Rcnstr Diamonds Wrkd Nt Suitbl For Jewelry (gm)",
        "total": -4026429
      },
      {
        "id": "hs8_71049910",
        "hsCode": "71",
        "hs4Code": "7104",
        "hs6Code": "710499",
        "hs8Code": "71049910",
        "name": "71049910 Syn/ Recon, Gemstones, Cut But Not Set For Jewelry (no)",
        "total": -11952140
      },
      {
        "id": "hs8_71049950",
        "hsCode": "71",
        "hs4Code": "7104",
        "hs6Code": "710499",
        "hs8Code": "71049950",
        "name": "71049950 Syn, Rcnstr Gmstones Wrkd Nt Suitbl For Jewelry (gm)",
        "total": -661369
      },
      {
        "id": "hs8_71051000",
        "hsCode": "71",
        "hs4Code": "7105",
        "hs6Code": "710510",
        "hs8Code": "71051000",
        "name": "71051000 Diam Pwdr Dst Ntrl 80 Ms Or Less (car)",
        "total": -1373065
      },
      {
        "id": "hs8_71059000",
        "hsCode": "71",
        "hs4Code": "7105",
        "hs6Code": "710590",
        "hs8Code": "71059000",
        "name": "71059000 DUST AND POWDER OF OTHER PRECIOUS STONES",
        "total": -40706
      },
      {
        "id": "hs8_71061000",
        "hsCode": "71",
        "hs4Code": "7106",
        "hs6Code": "710610",
        "hs8Code": "71061000",
        "name": "71061000 SILVER IN POWDER FORM",
        "total": -83104
      },
      {
        "id": "hs8_71069110",
        "hsCode": "71",
        "hs4Code": "7106",
        "hs6Code": "710691",
        "hs8Code": "71069110",
        "name": "71069110 GRAINS",
        "total": -19980192
      },
      {
        "id": "hs8_71069150",
        "hsCode": "71",
        "hs4Code": "7106",
        "hs6Code": "710691",
        "hs8Code": "71069150",
        "name": "71069150 Unwrought Silver, Nesoi (gm)",
        "total": -37064
      },
      {
        "id": "hs8_71069210",
        "hsCode": "71",
        "hs4Code": "7106",
        "hs6Code": "710692",
        "hs8Code": "71069210",
        "name": "71069210 SHEETS PLATES STRIPS TUBES AND PIPES OF SLVR",
        "total": 1719027
      },
      {
        "id": "hs8_71069250",
        "hsCode": "71",
        "hs4Code": "7106",
        "hs6Code": "710692",
        "hs8Code": "71069250",
        "name": "71069250 Silver, Semimanufactured (gm)",
        "total": -9402574
      },
      {
        "id": "hs8_71070000",
        "hsCode": "71",
        "hs4Code": "7107",
        "hs6Code": "710700",
        "hs8Code": "71070000",
        "name": "71070000 BASE MATL CLAD WTH SLVR ONLY SEMI MNFCTRD",
        "total": 867963
      },
      {
        "id": "hs8_71081100",
        "hsCode": "71",
        "hs4Code": "7108",
        "hs6Code": "710811",
        "hs8Code": "71081100",
        "name": "71081100 NON-MONETARY POWDER OF GOLD",
        "total": -9570
      },
      {
        "id": "hs8_71081210",
        "hsCode": "71",
        "hs4Code": "7108",
        "hs6Code": "710812",
        "hs8Code": "71081210",
        "name": "71081210 GOLD",
        "total": 61714960
      },
      {
        "id": "hs8_71081310",
        "hsCode": "71",
        "hs4Code": "7108",
        "hs6Code": "710813",
        "hs8Code": "71081310",
        "name": "71081310 GOLD",
        "total": 73690000
      },
      {
        "id": "hs8_71081355",
        "hsCode": "71",
        "hs4Code": "7108",
        "hs6Code": "710813",
        "hs8Code": "71081355",
        "name": "71081355 Gold, Semimanufactured, 99.5% Pure, Nt Othwse Mked (gm)",
        "total": -1029602
      },
      {
        "id": "hs8_71081370",
        "hsCode": "71",
        "hs4Code": "7108",
        "hs6Code": "710813",
        "hs8Code": "71081370",
        "name": "71081370 Gold, Semimanufactured, Nesoi, Nonmonetary (gm)",
        "total": -8795
      },
      {
        "id": "hs8_71090000",
        "hsCode": "71",
        "hs4Code": "7109",
        "hs6Code": "710900",
        "hs8Code": "71090000",
        "name": "71090000 SEMI MNFCTRD BASE MTLS/SLVR CLAD WTH GOLD",
        "total": 20000
      },
      {
        "id": "hs8_71101100",
        "hsCode": "71",
        "hs4Code": "7110",
        "hs6Code": "711011",
        "hs8Code": "71101100",
        "name": "71101100 Grain And Nuggets Of The Metal Platinum (cgm)",
        "total": -68509605
      },
      {
        "id": "hs8_71101900",
        "hsCode": "71",
        "hs4Code": "7110",
        "hs6Code": "711019",
        "hs8Code": "71101900",
        "name": "71101900 PLATINUM IN OTHER FORMS",
        "total": 504849
      },
      {
        "id": "hs8_71102100",
        "hsCode": "71",
        "hs4Code": "7110",
        "hs6Code": "711021",
        "hs8Code": "71102100",
        "name": "71102100 PALLADIUM UNWROUGHT OR IN POWDER FORM",
        "total": 6496130
      },
      {
        "id": "hs8_71102900",
        "hsCode": "71",
        "hs4Code": "7110",
        "hs6Code": "711029",
        "hs8Code": "71102900",
        "name": "71102900 PALLADIUM IN OTHER FORM",
        "total": 8485517
      },
      {
        "id": "hs8_71103100",
        "hsCode": "71",
        "hs4Code": "7110",
        "hs6Code": "711031",
        "hs8Code": "71103100",
        "name": "71103100 RHODIUM UNWROUGHT OR IN POWDER FORM",
        "total": -5599862
      },
      {
        "id": "hs8_71103900",
        "hsCode": "71",
        "hs4Code": "7110",
        "hs6Code": "711039",
        "hs8Code": "71103900",
        "name": "71103900 OTHER RHODIUM",
        "total": 2880000
      },
      {
        "id": "hs8_71104100",
        "hsCode": "71",
        "hs4Code": "7110",
        "hs6Code": "711041",
        "hs8Code": "71104100",
        "name": "71104100 IRIDIUM OSMIUM AND RUTHENIUM UNWROUGHT      OR IN POWDER FORM",
        "total": 972689
      },
      {
        "id": "hs8_71104900",
        "hsCode": "71",
        "hs4Code": "7110",
        "hs6Code": "711049",
        "hs8Code": "71104900",
        "name": "71104900 OTHR IRIDIUM OSMIUM AND RUTHENIUM",
        "total": 1310000
      },
      {
        "id": "hs8_71110000",
        "hsCode": "71",
        "hs4Code": "7111",
        "hs6Code": "711100",
        "hs8Code": "71110000",
        "name": "71110000 SMI MNFCTRD BS MTLS;SLVR/GLD,CLD WTH PLTNM",
        "total": 0
      },
      {
        "id": "hs8_71123001",
        "hsCode": "71",
        "hs4Code": "7112",
        "hs6Code": "711230",
        "hs8Code": "71123001",
        "name": "71123001 Ash Containing Precious Metal/precious Metal Comp (kg)",
        "total": -854964
      },
      {
        "id": "hs8_71129201",
        "hsCode": "71",
        "hs4Code": "7112",
        "hs6Code": "711292",
        "hs8Code": "71129201",
        "name": "71129201 Platinum Waste/scrap; Including Metal Clad With Pt (gm)",
        "total": -13049744
      },
      {
        "id": "hs8_71129901",
        "hsCode": "71",
        "hs4Code": "7112",
        "hs6Code": "711299",
        "hs8Code": "71129901",
        "name": "71129901 Wst&scrap Of Prec Mtl/mtl Clad W/prec Mtl, Nesoi (gm)",
        "total": -4072776
      },
      {
        "id": "hs8_71131110",
        "hsCode": "71",
        "hs4Code": "7113",
        "hs6Code": "711311",
        "hs8Code": "71131110",
        "name": "71131110 SILVER FILLIGREE WORK",
        "total": -1585539
      },
      {
        "id": "hs8_71131120",
        "hsCode": "71",
        "hs4Code": "7113",
        "hs6Code": "711311",
        "hs8Code": "71131120",
        "name": "71131120 Silver Jewelry, Not Over $18/doz Pcs Or Pts, Nesoi (gm)",
        "total": -5734418
      },
      {
        "id": "hs8_71131150",
        "hsCode": "71",
        "hs4Code": "7113",
        "hs6Code": "711311",
        "hs8Code": "71131150",
        "name": "71131150 Silver Jewelry, Val Over $18/doz Pcs Or Pts, Nesoi (gm)",
        "total": -659776118
      },
      {
        "id": "hs8_71131910",
        "hsCode": "71",
        "hs4Code": "7113",
        "hs6Code": "711319",
        "hs8Code": "71131910",
        "name": "71131910 Gld O Pltnm Rp Etc Stbl F Use Mnfctr Of Jwlry (gm)",
        "total": -3728261
      },
      {
        "id": "hs8_71131921",
        "hsCode": "71",
        "hs4Code": "7113",
        "hs6Code": "711319",
        "hs8Code": "71131921",
        "name": "71131921 Of platinum, Unstudded",
        "total": 25502258
      },
      {
        "id": "hs8_71131925",
        "hsCode": "71",
        "hs4Code": "7113",
        "hs6Code": "711319",
        "hs8Code": "71131925",
        "name": "71131925 Of platinum, Studded with other precious and semi-precious stones",
        "total": -9513749
      },
      {
        "id": "hs8_71131929",
        "hsCode": "71",
        "hs4Code": "7113",
        "hs6Code": "711319",
        "hs8Code": "71131929",
        "name": "71131929 Other",
        "total": -467625301
      },
      {
        "id": "hs8_71131930",
        "hsCode": "71",
        "hs4Code": "7113",
        "hs6Code": "711319",
        "hs8Code": "71131930",
        "name": "71131930 Gold Clasps And Parts Thereof (gm)",
        "total": -2580672
      },
      {
        "id": "hs8_71131950",
        "hsCode": "71",
        "hs4Code": "7113",
        "hs6Code": "711319",
        "hs8Code": "71131950",
        "name": "71131950 Platinum Necklaces And Neck Chains (pcs)",
        "total": -4624394632
      },
      {
        "id": "hs8_71132010",
        "hsCode": "71",
        "hs4Code": "7113",
        "hs6Code": "711320",
        "hs8Code": "71132010",
        "name": "71132010 Chn Etc Cl Plt W P M F Mnfr Jwlry Etc (gm)",
        "total": -14955
      },
      {
        "id": "hs8_71132021",
        "hsCode": "71",
        "hs4Code": "7113",
        "hs6Code": "711320",
        "hs8Code": "71132021",
        "name": "71132021 Rope Nckls A Nck Ch O Bs Mtl Cld W Gold (gm)",
        "total": -6958
      },
      {
        "id": "hs8_71132025",
        "hsCode": "71",
        "hs4Code": "7113",
        "hs6Code": "711320",
        "hs8Code": "71132025",
        "name": "71132025 Mxd Lnk Nckls A Chns Bs Mtl Cld W Gold (gm)",
        "total": -4918
      },
      {
        "id": "hs8_71132029",
        "hsCode": "71",
        "hs4Code": "7113",
        "hs6Code": "711320",
        "hs8Code": "71132029",
        "name": "71132029 Ncklcs A Nck Chns Nesoi Base Mtl Clad W Gold (gm)",
        "total": -68063
      },
      {
        "id": "hs8_71132030",
        "hsCode": "71",
        "hs4Code": "7113",
        "hs6Code": "711320",
        "hs8Code": "71132030",
        "name": "71132030 Clsps A Pts Of Base Mtl Clad W Prec Metal (gm)",
        "total": -58184
      },
      {
        "id": "hs8_71132050",
        "hsCode": "71",
        "hs4Code": "7113",
        "hs6Code": "711320",
        "hs8Code": "71132050",
        "name": "71132050 Jwlry Nesoi Of Base Mtl Clad W Precious Metal (gm)",
        "total": -8414552
      },
      {
        "id": "hs8_71141110",
        "hsCode": "71",
        "hs4Code": "7114",
        "hs6Code": "711411",
        "hs8Code": "71141110",
        "name": "71141110 MANUFACTURES OF SILVER",
        "total": 33072039
      },
      {
        "id": "hs8_71141120",
        "hsCode": "71",
        "hs4Code": "7114",
        "hs6Code": "711411",
        "hs8Code": "71141120",
        "name": "71141120 PARTS",
        "total": 40000
      },
      {
        "id": "hs8_71141130",
        "hsCode": "71",
        "hs4Code": "7114",
        "hs6Code": "711411",
        "hs8Code": "71141130",
        "name": "71141130 Spoons And Ladles With Sterling Silver Handles (no)",
        "total": -17833
      },
      {
        "id": "hs8_71141140",
        "hsCode": "71",
        "hs4Code": "7114",
        "hs6Code": "711411",
        "hs8Code": "71141140",
        "name": "71141140 Spoons And Ladles With Handles Of Gold Or Plat (no)",
        "total": -64351
      },
      {
        "id": "hs8_71141145",
        "hsCode": "71",
        "hs4Code": "7114",
        "hs6Code": "711411",
        "hs8Code": "71141145",
        "name": "71141145 Sets, Strl Slvr, Of Knvs Frks Spns Ladls (pcs)",
        "total": -6329
      },
      {
        "id": "hs8_71141150",
        "hsCode": "71",
        "hs4Code": "7114",
        "hs6Code": "711411",
        "hs8Code": "71141150",
        "name": "71141150 Sterling Silver Tableware, Nesoi (gm)",
        "total": -532627
      },
      {
        "id": "hs8_71141160",
        "hsCode": "71",
        "hs4Code": "7114",
        "hs6Code": "711411",
        "hs8Code": "71141160",
        "name": "71141160 Slvr Artls Nesoi F hh Ktchn, Tlt A Sntry Wrs (gm)",
        "total": -235121
      },
      {
        "id": "hs8_71141170",
        "hsCode": "71",
        "hs4Code": "7114",
        "hs6Code": "711411",
        "hs8Code": "71141170",
        "name": "71141170 Silver Arts Nesoi (gm)",
        "total": -7133960
      },
      {
        "id": "hs8_71141900",
        "hsCode": "71",
        "hs4Code": "7114",
        "hs6Code": "711419",
        "hs8Code": "71141900",
        "name": "71141900 Artls Of Gld Or Plat Nesoi (gm)",
        "total": -351662
      },
      {
        "id": "hs8_71142000",
        "hsCode": "71",
        "hs4Code": "7114",
        "hs6Code": "711420",
        "hs8Code": "71142000",
        "name": "71142000 Artcls Nesoi Of Bs Mtl Clad W Pr Mt hh K Tb T S W (gm)",
        "total": -480100
      },
      {
        "id": "hs8_71151000",
        "hsCode": "71",
        "hs4Code": "7115",
        "hs6Code": "711510",
        "hs8Code": "71151000",
        "name": "71151000 CTLYSTS IN WIRE CLOTH/GRIL FORM OF PLTNM",
        "total": 640000
      },
      {
        "id": "hs8_71159005",
        "hsCode": "71",
        "hs4Code": "7115",
        "hs6Code": "711590",
        "hs8Code": "71159005",
        "name": "71159005 Artcls Of Pre Met, Rec Shpe, 99.5% Pure, Of Gold (gm)",
        "total": -29178843
      },
      {
        "id": "hs8_71159030",
        "hsCode": "71",
        "hs4Code": "7115",
        "hs6Code": "711590",
        "hs8Code": "71159030",
        "name": "71159030 Artcls Nesoi Of Gld Incl Mtl Cld W Gold (gm)",
        "total": -20649
      },
      {
        "id": "hs8_71159040",
        "hsCode": "71",
        "hs4Code": "7115",
        "hs6Code": "711590",
        "hs8Code": "71159040",
        "name": "71159040 Artcls Nesoi Of Slvr Incl Mtl Cld W Slvr (gm)",
        "total": -246076
      },
      {
        "id": "hs8_71159060",
        "hsCode": "71",
        "hs4Code": "7115",
        "hs6Code": "711590",
        "hs8Code": "71159060",
        "name": "71159060 Artcls Nesoi Of Plat Incl Mtl Clad W Plat (gm)",
        "total": -144237
      },
      {
        "id": "hs8_71161010",
        "hsCode": "71",
        "hs4Code": "7116",
        "hs6Code": "711610",
        "hs8Code": "71161010",
        "name": "71161010 Articles Of Natural Pearls (gm)",
        "total": -58571
      },
      {
        "id": "hs8_71161025",
        "hsCode": "71",
        "hs4Code": "7116",
        "hs6Code": "711610",
        "hs8Code": "71161025",
        "name": "71161025 Articles Of Cultured Pearls (gm)",
        "total": -237710
      },
      {
        "id": "hs8_71162005",
        "hsCode": "71",
        "hs4Code": "7116",
        "hs6Code": "711620",
        "hs8Code": "71162005",
        "name": "71162005 Jewelry Of Precious/semiprecious Stones Lt=$40 Ea (gm)",
        "total": -53579615
      },
      {
        "id": "hs8_71162015",
        "hsCode": "71",
        "hs4Code": "7116",
        "hs6Code": "711620",
        "hs8Code": "71162015",
        "name": "71162015 Jewelry Of Precious/semiprecious Stones Gt $40 Ea (gm)",
        "total": -9380356
      },
      {
        "id": "hs8_71162030",
        "hsCode": "71",
        "hs4Code": "7116",
        "hs6Code": "711620",
        "hs8Code": "71162030",
        "name": "71162030 Graded Semiprec Stones Strung Temprly Fr Trnspt (gm)",
        "total": -925336
      },
      {
        "id": "hs8_71162035",
        "hsCode": "71",
        "hs4Code": "7116",
        "hs6Code": "711620",
        "hs8Code": "71162035",
        "name": "71162035 Figurines Of Semiprecious Stone (not Rock Crystal) (no)",
        "total": -785491
      },
      {
        "id": "hs8_71162040",
        "hsCode": "71",
        "hs4Code": "7116",
        "hs6Code": "711620",
        "hs8Code": "71162040",
        "name": "71162040 Oth Artcls Of Smiprec Stones (exc Rock Crystal) (no)",
        "total": -4400047
      },
      {
        "id": "hs8_71162050",
        "hsCode": "71",
        "hs4Code": "7116",
        "hs6Code": "711620",
        "hs8Code": "71162050",
        "name": "71162050 Artcls Of Prec Semiprec Or Synthetic Stones Nesoi (no)",
        "total": -54990485
      },
      {
        "id": "hs8_71171100",
        "hsCode": "71",
        "hs4Code": "7117",
        "hs6Code": "711711",
        "hs8Code": "71171100",
        "name": "71171100 CUFF LINKS AND STUDS OF BASE METAL W/N      PLATED WITH PRECIOUS METAL",
        "total": 341762
      },
      {
        "id": "hs8_71171905",
        "hsCode": "71",
        "hs4Code": "7117",
        "hs6Code": "711719",
        "hs8Code": "71171905",
        "name": "71171905 Toy Jwlry,bs Mt Chain,rope,cable,etc Nov 8 Cts Ea (kg)",
        "total": -82930
      },
      {
        "id": "hs8_71171915",
        "hsCode": "71",
        "hs4Code": "7117",
        "hs6Code": "711719",
        "hs8Code": "71171915",
        "name": "71171915 Oth Bs Mtl Chain,cable,rope,etc Nov 33 Cents Meter (kg)",
        "total": -283962
      },
      {
        "id": "hs8_71171920",
        "hsCode": "71",
        "hs4Code": "7117",
        "hs6Code": "711719",
        "hs8Code": "71171920",
        "name": "71171920 GERMAN SILVER JEWELLERY",
        "total": 214883
      },
      {
        "id": "hs8_71171930",
        "hsCode": "71",
        "hs4Code": "7117",
        "hs6Code": "711719",
        "hs8Code": "71171930",
        "name": "71171930 Religious Artcls Bs Mtl Devot Typ T B Wrn O Car (kg)",
        "total": -229460
      },
      {
        "id": "hs8_71171960",
        "hsCode": "71",
        "hs4Code": "7117",
        "hs6Code": "711719",
        "hs8Code": "71171960",
        "name": "71171960 Othr Toy Jewelry, Base Metal, Not Over 8 Cents Ea (kg)",
        "total": -39255
      },
      {
        "id": "hs8_71171990",
        "hsCode": "71",
        "hs4Code": "7117",
        "hs6Code": "711719",
        "hs8Code": "71171990",
        "name": "71171990 OTHER",
        "total": 35796644
      },
      {
        "id": "hs8_71179010",
        "hsCode": "71",
        "hs4Code": "7117",
        "hs6Code": "711790",
        "hs8Code": "71179010",
        "name": "71179010 JEWELLERY SET WITH IMITATION PEARLS       OR IMITATION OR SYNTHETIC STONES",
        "total": 21439382
      },
      {
        "id": "hs8_71179020",
        "hsCode": "71",
        "hs4Code": "7117",
        "hs6Code": "711790",
        "hs8Code": "71179020",
        "name": "71179020 Rosaries And Chaplets Excpt Base Metal (kg)",
        "total": -219105
      },
      {
        "id": "hs8_71179030",
        "hsCode": "71",
        "hs4Code": "7117",
        "hs6Code": "711790",
        "hs8Code": "71179030",
        "name": "71179030 Rel Arts Nesoi T B Wrn O Crd O Th Persn (kg)",
        "total": -1775847
      },
      {
        "id": "hs8_71179055",
        "hsCode": "71",
        "hs4Code": "7117",
        "hs6Code": "711790",
        "hs8Code": "71179055",
        "name": "71179055 Oth Imit Jwlry Nt Mtl Nov $.20 Pr Doz Pcs Or Pts (kg)",
        "total": -161244
      },
      {
        "id": "hs8_71179060",
        "hsCode": "71",
        "hs4Code": "7117",
        "hs6Code": "711790",
        "hs8Code": "71179060",
        "name": "71179060 Toy Jwlry, Not Metal, Nov 8 Cents Ea (excpt Prts) (kg)",
        "total": -57868
      },
      {
        "id": "hs8_71179075",
        "hsCode": "71",
        "hs4Code": "7117",
        "hs6Code": "711790",
        "hs8Code": "71179075",
        "name": "71179075 Othr Imit Jwlry Plstcs Ov $.20 Pr Dz Pcs O Pts (kg)",
        "total": -3645001
      },
      {
        "id": "hs8_71179090",
        "hsCode": "71",
        "hs4Code": "7117",
        "hs6Code": "711790",
        "hs8Code": "71179090",
        "name": "71179090 OTHER IMITATION JEWELLERY FOR PERSONAL    ADORNMENT(OTHER THAN ARTWARE)",
        "total": 194979854
      },
      {
        "id": "hs8_71181000",
        "hsCode": "71",
        "hs4Code": "7118",
        "hs6Code": "711810",
        "hs8Code": "71181000",
        "name": "71181000 COIN(EXCL GOLD)NOT BEING LEGAL TENDER",
        "total": 3003606
      },
      {
        "id": "hs8_71189000",
        "hsCode": "71",
        "hs4Code": "7118",
        "hs6Code": "711890",
        "hs8Code": "71189000",
        "name": "71189000 OTHER COIN",
        "total": 181885707
      }
    ],
    "rows": [
      {
        "periodKey": "2024-01",
        "periodLabel": "Jan 2024",
        "periodSort": 202401,
        "hs8_71012100": 0,
        "hs8_71012260": -17004,
        "hs8_71021000": 0,
        "hs8_71022110": 351975,
        "hs8_71022900": -110773,
        "hs8_71023100": 59566000,
        "hs8_71023900": -469093706,
        "hs8_71031020": -424851,
        "hs8_71031040": -14016,
        "hs8_71039100": -30375498,
        "hs8_71039910": -22541338,
        "hs8_71039950": -190181,
        "hs8_71041000": -27712,
        "hs8_71042100": -452508,
        "hs8_71042900": 20000,
        "hs8_71049110": -97215528,
        "hs8_71049150": -67742,
        "hs8_71049910": -39180,
        "hs8_71049950": -24550,
        "hs8_71051000": -105756,
        "hs8_71059000": 0,
        "hs8_71061000": -1303,
        "hs8_71069110": 0,
        "hs8_71069210": 10000,
        "hs8_71069250": -287140,
        "hs8_71070000": -2624,
        "hs8_71081100": 0,
        "hs8_71090000": 10000,
        "hs8_71101100": -4214032,
        "hs8_71101900": 460000,
        "hs8_71102100": -1719,
        "hs8_71102900": 330000,
        "hs8_71103100": 0,
        "hs8_71103900": 0,
        "hs8_71104100": 0,
        "hs8_71104900": 100000,
        "hs8_71110000": 0,
        "hs8_71123001": -464142,
        "hs8_71131110": -53559,
        "hs8_71131120": -304603,
        "hs8_71131150": -26030862,
        "hs8_71131910": -26885,
        "hs8_71131921": 347009,
        "hs8_71131925": -480691,
        "hs8_71131929": -16453540,
        "hs8_71131930": -84908,
        "hs8_71131950": -177732414,
        "hs8_71132021": -2964,
        "hs8_71132029": -10432,
        "hs8_71132050": -41376,
        "hs8_71141110": 660000,
        "hs8_71141120": 20000,
        "hs8_71141130": -5441,
        "hs8_71141150": -25344,
        "hs8_71141170": -195345,
        "hs8_71141900": -4737,
        "hs8_71151000": 0,
        "hs8_71159005": -11453,
        "hs8_71159060": -22136,
        "hs8_71161010": -35806,
        "hs8_71161025": -17359,
        "hs8_71162005": -1748851,
        "hs8_71162015": -557988,
        "hs8_71162030": -124907,
        "hs8_71162035": -38512,
        "hs8_71162040": -245687,
        "hs8_71162050": -2606284,
        "hs8_71171100": 8000,
        "hs8_71171920": 10000,
        "hs8_71171930": -4937,
        "hs8_71171960": -4060,
        "hs8_71171990": 1643238,
        "hs8_71179010": 760000,
        "hs8_71179030": -91094,
        "hs8_71179055": -3195,
        "hs8_71179075": -181940,
        "hs8_71179090": 8401891,
        "hs8_71181000": -349759,
        "hs8_71189000": 16008842
      },
      {
        "periodKey": "2024-02",
        "periodLabel": "Feb 2024",
        "periodSort": 202402,
        "hs8_71012100": 340000,
        "hs8_71012260": -12451,
        "hs8_71021000": 0,
        "hs8_71022110": 434500,
        "hs8_71022140": -5408,
        "hs8_71022900": -29713,
        "hs8_71023100": 175070000,
        "hs8_71023900": -590507488,
        "hs8_71031020": -281284,
        "hs8_71031040": -8075,
        "hs8_71039100": -9149537,
        "hs8_71039910": -1935077,
        "hs8_71039950": -93627,
        "hs8_71041000": -3798,
        "hs8_71042100": -42546,
        "hs8_71042900": 4930,
        "hs8_71049110": -90031956,
        "hs8_71049150": -270214,
        "hs8_71049910": -84355,
        "hs8_71049950": -55872,
        "hs8_71051000": -61433,
        "hs8_71059000": -25324,
        "hs8_71061000": -1089,
        "hs8_71069110": 50000,
        "hs8_71069210": 40000,
        "hs8_71069250": -288405,
        "hs8_71070000": 0,
        "hs8_71081100": 0,
        "hs8_71090000": 0,
        "hs8_71101900": 0,
        "hs8_71102100": 0,
        "hs8_71102900": 0,
        "hs8_71103100": 40000,
        "hs8_71103900": 0,
        "hs8_71104100": 0,
        "hs8_71104900": 0,
        "hs8_71110000": 0,
        "hs8_71129901": -298979,
        "hs8_71131110": 10248,
        "hs8_71131120": -216687,
        "hs8_71131150": -21652013,
        "hs8_71131910": -55112,
        "hs8_71131921": 159923,
        "hs8_71131925": -586938,
        "hs8_71131929": -19257033,
        "hs8_71131930": -94214,
        "hs8_71131950": -186028906,
        "hs8_71132050": -38898,
        "hs8_71141110": 460000,
        "hs8_71141120": 0,
        "hs8_71141140": -3505,
        "hs8_71141150": -4454,
        "hs8_71141170": -244133,
        "hs8_71151000": 0,
        "hs8_71159060": -4702,
        "hs8_71161025": -4620,
        "hs8_71162005": -2116315,
        "hs8_71162015": -209917,
        "hs8_71162030": -43624,
        "hs8_71162035": -15100,
        "hs8_71162040": -228881,
        "hs8_71162050": -1507463,
        "hs8_71171100": 4941,
        "hs8_71171920": 0,
        "hs8_71171930": -5596,
        "hs8_71171990": 2069949,
        "hs8_71179010": 780000,
        "hs8_71179030": -104080,
        "hs8_71179055": -3219,
        "hs8_71179075": -174283,
        "hs8_71179090": 8140605,
        "hs8_71181000": -153179,
        "hs8_71189000": 15050000
      },
      {
        "periodKey": "2024-03",
        "periodLabel": "Mar 2024",
        "periodSort": 202403,
        "hs8_71012100": 0,
        "hs8_71012230": -14401,
        "hs8_71012260": -5724,
        "hs8_71021000": -17650,
        "hs8_71022110": 109650,
        "hs8_71022140": -2000,
        "hs8_71022900": -25422,
        "hs8_71023100": 90450000,
        "hs8_71023900": -591084161,
        "hs8_71031020": -167985,
        "hs8_71031040": -23313,
        "hs8_71039100": -15583312,
        "hs8_71039910": -5533225,
        "hs8_71039950": -160257,
        "hs8_71041000": -4500,
        "hs8_71042100": -653133,
        "hs8_71042900": 44930,
        "hs8_71049110": -78762677,
        "hs8_71049150": -107422,
        "hs8_71049910": -213309,
        "hs8_71049950": -15701,
        "hs8_71051000": -30253,
        "hs8_71059000": -3416,
        "hs8_71061000": 0,
        "hs8_71069110": 50000,
        "hs8_71069210": 50000,
        "hs8_71069250": -163832,
        "hs8_71070000": -3428,
        "hs8_71081100": 0,
        "hs8_71090000": 0,
        "hs8_71101100": -285031,
        "hs8_71101900": 380000,
        "hs8_71102100": 327849,
        "hs8_71102900": 230000,
        "hs8_71103100": 2830000,
        "hs8_71103900": 0,
        "hs8_71104100": 260000,
        "hs8_71104900": 0,
        "hs8_71110000": 0,
        "hs8_71129201": -369713,
        "hs8_71129901": -387733,
        "hs8_71131110": 88,
        "hs8_71131120": -283737,
        "hs8_71131150": -25092911,
        "hs8_71131910": -67829,
        "hs8_71131921": 264411,
        "hs8_71131925": -531590,
        "hs8_71131929": -20619821,
        "hs8_71131930": -27002,
        "hs8_71131950": -206827417,
        "hs8_71132010": -5429,
        "hs8_71132050": -69883,
        "hs8_71141110": 620000,
        "hs8_71141120": 0,
        "hs8_71141150": -19345,
        "hs8_71141160": -19991,
        "hs8_71141170": -115615,
        "hs8_71141900": -8067,
        "hs8_71142000": -5041,
        "hs8_71151000": 0,
        "hs8_71159005": -6810,
        "hs8_71159040": -20207,
        "hs8_71161025": -10626,
        "hs8_71162005": -1986796,
        "hs8_71162015": -92891,
        "hs8_71162030": -29368,
        "hs8_71162035": -57988,
        "hs8_71162040": -153697,
        "hs8_71162050": -2880543,
        "hs8_71171100": 4840,
        "hs8_71171915": -4116,
        "hs8_71171920": -6244,
        "hs8_71171930": -2936,
        "hs8_71171960": -9096,
        "hs8_71171990": 1331528,
        "hs8_71179010": 640000,
        "hs8_71179030": -35865,
        "hs8_71179055": -9225,
        "hs8_71179075": -207128,
        "hs8_71179090": 9322960,
        "hs8_71181000": -100691,
        "hs8_71189000": 135261042
      },
      {
        "periodKey": "2024-04",
        "periodLabel": "Apr 2024",
        "periodSort": 202404,
        "hs8_71011030": -9570,
        "hs8_71012100": 0,
        "hs8_71012260": -3716,
        "hs8_71021000": 0,
        "hs8_71022110": 540000,
        "hs8_71022130": -5313,
        "hs8_71022140": -3000,
        "hs8_71022900": -48542,
        "hs8_71023100": 65879999.99999999,
        "hs8_71023900": -590659164,
        "hs8_71031020": -270747,
        "hs8_71031040": -135637,
        "hs8_71039100": -7829795,
        "hs8_71039910": -4752531,
        "hs8_71039950": -161815,
        "hs8_71041000": 0,
        "hs8_71042100": -410086,
        "hs8_71042900": 30000,
        "hs8_71049110": -72571565,
        "hs8_71049150": -213699,
        "hs8_71049910": -308758,
        "hs8_71049950": -4200,
        "hs8_71051000": -44713,
        "hs8_71059000": 0,
        "hs8_71061000": -5475,
        "hs8_71069110": 0,
        "hs8_71069150": -37064,
        "hs8_71069210": 0,
        "hs8_71069250": -367711,
        "hs8_71070000": 0,
        "hs8_71081100": 0,
        "hs8_71081210": 0,
        "hs8_71081310": 0,
        "hs8_71081370": -5860,
        "hs8_71090000": 0,
        "hs8_71101900": 420000,
        "hs8_71102100": 0,
        "hs8_71102900": 200000,
        "hs8_71103100": 20280000,
        "hs8_71103900": 110000,
        "hs8_71104100": 0,
        "hs8_71104900": 0,
        "hs8_71110000": 0,
        "hs8_71129201": -403643,
        "hs8_71131110": -33126,
        "hs8_71131120": -308463,
        "hs8_71131150": -24325913,
        "hs8_71131910": -185490,
        "hs8_71131921": 441618,
        "hs8_71131925": -304015,
        "hs8_71131929": -22637401,
        "hs8_71131930": -174023,
        "hs8_71131950": -233824559,
        "hs8_71132025": -4918,
        "hs8_71132050": -70697,
        "hs8_71141110": 836696,
        "hs8_71141120": 0,
        "hs8_71141130": -2673,
        "hs8_71141150": -12415,
        "hs8_71141160": -70349,
        "hs8_71141170": -250633,
        "hs8_71142000": -2760,
        "hs8_71151000": 0,
        "hs8_71159040": -36635,
        "hs8_71159060": -11215,
        "hs8_71161025": -10102,
        "hs8_71162005": -1357917,
        "hs8_71162015": -362545,
        "hs8_71162030": -28389,
        "hs8_71162035": -63719,
        "hs8_71162040": -134735,
        "hs8_71162050": -2220987,
        "hs8_71171100": -8983,
        "hs8_71171920": 20000,
        "hs8_71171990": 1090436,
        "hs8_71179010": 530000,
        "hs8_71179030": -76089,
        "hs8_71179055": -5352,
        "hs8_71179075": -164777,
        "hs8_71179090": 7020874,
        "hs8_71181000": -187313,
        "hs8_71189000": -116094
      },
      {
        "periodKey": "2024-05",
        "periodLabel": "May 2024",
        "periodSort": 202405,
        "hs8_71011060": -11373,
        "hs8_71012100": -2083511,
        "hs8_71012260": -2493,
        "hs8_71021000": -38550,
        "hs8_71022110": 149000,
        "hs8_71022130": -29840,
        "hs8_71022900": -81491,
        "hs8_71023100": 29970000,
        "hs8_71023900": -1060687631,
        "hs8_71031020": -222328,
        "hs8_71039100": -37810470,
        "hs8_71039910": -21649474,
        "hs8_71039950": -194843,
        "hs8_71041000": 0,
        "hs8_71042100": -226788,
        "hs8_71042900": 34930,
        "hs8_71049110": -86887594,
        "hs8_71049150": -248284,
        "hs8_71049910": -869861,
        "hs8_71049950": -3000,
        "hs8_71051000": -23075,
        "hs8_71059000": -20666,
        "hs8_71061000": -7998,
        "hs8_71069110": 0,
        "hs8_71069210": 0,
        "hs8_71069250": -268571,
        "hs8_71070000": 123461,
        "hs8_71081100": 0,
        "hs8_71081210": 0,
        "hs8_71081310": 0,
        "hs8_71081370": -2935,
        "hs8_71090000": 0,
        "hs8_71101900": 570000,
        "hs8_71102100": 20000,
        "hs8_71102900": 160000,
        "hs8_71103100": 0,
        "hs8_71103900": 0,
        "hs8_71104100": 0,
        "hs8_71104900": 0,
        "hs8_71110000": 0,
        "hs8_71129901": -653426,
        "hs8_71131110": -32852,
        "hs8_71131120": -304275,
        "hs8_71131150": -22898426,
        "hs8_71131910": -169410,
        "hs8_71131921": 1182057,
        "hs8_71131925": -738790,
        "hs8_71131929": -27607702,
        "hs8_71131930": -104772,
        "hs8_71131950": -225227386,
        "hs8_71132029": -17080,
        "hs8_71132050": -71878,
        "hs8_71141110": 1110000,
        "hs8_71141120": 0,
        "hs8_71141145": -2647,
        "hs8_71141150": -37443,
        "hs8_71141160": -4100,
        "hs8_71141170": -477450,
        "hs8_71142000": -17308,
        "hs8_71151000": 0,
        "hs8_71159040": -7073,
        "hs8_71159060": -2016,
        "hs8_71161025": -3058,
        "hs8_71162005": -2064691,
        "hs8_71162015": -229341,
        "hs8_71162030": -68948,
        "hs8_71162035": -66272,
        "hs8_71162040": -259485,
        "hs8_71162050": -2210127,
        "hs8_71171100": 24968,
        "hs8_71171920": 0,
        "hs8_71171930": -3378,
        "hs8_71171990": 1139838,
        "hs8_71179010": 825325,
        "hs8_71179030": -40101,
        "hs8_71179055": -11995,
        "hs8_71179075": -282614,
        "hs8_71179090": 7817124,
        "hs8_71181000": 48645,
        "hs8_71189000": 4130189
      },
      {
        "periodKey": "2024-06",
        "periodLabel": "Jun 2024",
        "periodSort": 202406,
        "hs8_71011060": -3403,
        "hs8_71012100": 1363,
        "hs8_71012260": -10380,
        "hs8_71021000": -49591,
        "hs8_71022110": 534750,
        "hs8_71022140": -18590,
        "hs8_71022900": -26422,
        "hs8_71023100": 102910000,
        "hs8_71023900": -446985390,
        "hs8_71031020": -101810,
        "hs8_71031040": -2320,
        "hs8_71039100": -19298652,
        "hs8_71039910": -3004443,
        "hs8_71039950": -186359,
        "hs8_71041000": -8432,
        "hs8_71042100": -50584,
        "hs8_71042900": 20000,
        "hs8_71049110": -64479799,
        "hs8_71049150": -213315,
        "hs8_71049910": -431250,
        "hs8_71049950": -48446,
        "hs8_71051000": -104860,
        "hs8_71059000": 0,
        "hs8_71061000": 300000,
        "hs8_71069110": 0,
        "hs8_71069210": 0,
        "hs8_71069250": -474292,
        "hs8_71070000": 0,
        "hs8_71081100": 0,
        "hs8_71081210": 0,
        "hs8_71081310": 0,
        "hs8_71090000": 0,
        "hs8_71101900": 700000,
        "hs8_71102100": 10000,
        "hs8_71102900": 0,
        "hs8_71103100": 5470000,
        "hs8_71103900": 0,
        "hs8_71104100": 0,
        "hs8_71104900": 0,
        "hs8_71110000": 0,
        "hs8_71129901": -734539,
        "hs8_71131110": -48621,
        "hs8_71131120": -266711,
        "hs8_71131150": -19498341,
        "hs8_71131910": -41268,
        "hs8_71131921": 943428,
        "hs8_71131925": -337511,
        "hs8_71131929": -14212700,
        "hs8_71131930": -38412,
        "hs8_71131950": -174590761,
        "hs8_71132050": -199800,
        "hs8_71141110": 900000,
        "hs8_71141120": 0,
        "hs8_71141150": -14541,
        "hs8_71141170": -437327,
        "hs8_71142000": -29990,
        "hs8_71151000": 0,
        "hs8_71159030": -18243,
        "hs8_71159040": -23299,
        "hs8_71161025": -19693,
        "hs8_71162005": -1490849,
        "hs8_71162015": -330944,
        "hs8_71162030": -25007,
        "hs8_71162035": -30971,
        "hs8_71162040": -144062,
        "hs8_71162050": -2002316,
        "hs8_71171100": 20000,
        "hs8_71171915": -4963,
        "hs8_71171920": 0,
        "hs8_71171990": 827891,
        "hs8_71179010": 783621,
        "hs8_71179030": -11689,
        "hs8_71179075": -164451,
        "hs8_71179090": 6395420,
        "hs8_71181000": -149991,
        "hs8_71189000": 6406882
      },
      {
        "periodKey": "2024-07",
        "periodLabel": "Jul 2024",
        "periodSort": 202407,
        "hs8_71012100": 0,
        "hs8_71012230": -19750,
        "hs8_71021000": 0,
        "hs8_71022110": 430000,
        "hs8_71022900": -49600,
        "hs8_71023100": 41390000,
        "hs8_71023900": -489689314,
        "hs8_71031020": -109873,
        "hs8_71031040": -6300,
        "hs8_71039100": -8728080,
        "hs8_71039910": -4267470,
        "hs8_71039950": -138620,
        "hs8_71041000": 0,
        "hs8_71042100": -131128,
        "hs8_71042900": 53786,
        "hs8_71049110": -73597788,
        "hs8_71049150": -179796,
        "hs8_71049910": -678232,
        "hs8_71049950": -150031,
        "hs8_71051000": -11471,
        "hs8_71059000": 0,
        "hs8_71061000": -259680,
        "hs8_71069110": 10920000,
        "hs8_71069210": -92974,
        "hs8_71069250": -638923,
        "hs8_71070000": -4181,
        "hs8_71081100": 0,
        "hs8_71081210": 0,
        "hs8_71081310": 0,
        "hs8_71090000": 0,
        "hs8_71101900": 350000,
        "hs8_71102100": 0,
        "hs8_71102900": 220000,
        "hs8_71103100": 5860000,
        "hs8_71103900": 0,
        "hs8_71104100": 0,
        "hs8_71104900": 0,
        "hs8_71110000": 0,
        "hs8_71129201": -172303,
        "hs8_71129901": -67895,
        "hs8_71131110": -21852,
        "hs8_71131120": -243074,
        "hs8_71131150": -24817631,
        "hs8_71131910": -245633,
        "hs8_71131921": 327868,
        "hs8_71131925": -412398,
        "hs8_71131929": -18455142,
        "hs8_71131930": -40301,
        "hs8_71131950": -212971845,
        "hs8_71132050": -140911,
        "hs8_71141110": 950000,
        "hs8_71141120": 0,
        "hs8_71141150": -6709,
        "hs8_71141160": -13207,
        "hs8_71141170": -247305,
        "hs8_71141900": -27360,
        "hs8_71142000": -18377,
        "hs8_71151000": 0,
        "hs8_71159005": -122164,
        "hs8_71159060": -7759,
        "hs8_71161025": -19345,
        "hs8_71162005": -2324147,
        "hs8_71162015": -263490,
        "hs8_71162030": -12307,
        "hs8_71162035": -4583,
        "hs8_71162040": -199221,
        "hs8_71162050": -1438962,
        "hs8_71171100": 23493,
        "hs8_71171920": 20000,
        "hs8_71171960": -5258,
        "hs8_71171990": 1005415,
        "hs8_71179010": 943782,
        "hs8_71179020": -2424,
        "hs8_71179030": -80606,
        "hs8_71179075": -99580,
        "hs8_71179090": 7435402.999999999,
        "hs8_71181000": 29407,
        "hs8_71189000": 4747548
      },
      {
        "periodKey": "2024-08",
        "periodLabel": "Aug 2024",
        "periodSort": 202408,
        "hs8_71011060": -9106,
        "hs8_71012100": -15860,
        "hs8_71012260": -4757,
        "hs8_71021000": 0,
        "hs8_71022110": 170000,
        "hs8_71022130": -12390,
        "hs8_71022900": -29226,
        "hs8_71023100": 28620000,
        "hs8_71023900": -482311297,
        "hs8_71031020": -99880,
        "hs8_71031040": -22117,
        "hs8_71039100": -15104571,
        "hs8_71039910": -4709432,
        "hs8_71039950": -258870,
        "hs8_71041000": 0,
        "hs8_71042100": -111982,
        "hs8_71042900": -3070,
        "hs8_71049110": -68935419,
        "hs8_71049150": -132100,
        "hs8_71049910": -688946,
        "hs8_71049950": -2097,
        "hs8_71051000": -23432,
        "hs8_71059000": 0,
        "hs8_71061000": 280413,
        "hs8_71069110": 0,
        "hs8_71069210": 10000,
        "hs8_71069250": -322261,
        "hs8_71070000": -2407,
        "hs8_71081100": 0,
        "hs8_71081210": 0,
        "hs8_71081310": 0,
        "hs8_71090000": 0,
        "hs8_71101100": -796105,
        "hs8_71101900": 10000,
        "hs8_71102100": 0,
        "hs8_71102900": 0,
        "hs8_71103100": 0,
        "hs8_71103900": 0,
        "hs8_71104100": 0,
        "hs8_71104900": 0,
        "hs8_71110000": 0,
        "hs8_71129901": -4610,
        "hs8_71131110": -29935,
        "hs8_71131120": -394702,
        "hs8_71131150": -29939457,
        "hs8_71131910": -65110,
        "hs8_71131921": 261987,
        "hs8_71131925": -544415,
        "hs8_71131929": -22855340,
        "hs8_71131930": -19104,
        "hs8_71131950": -222241270,
        "hs8_71132029": -5600,
        "hs8_71132050": -121842,
        "hs8_71141110": 1375015,
        "hs8_71141120": 0,
        "hs8_71141150": -36245,
        "hs8_71141170": -447741,
        "hs8_71142000": -47536,
        "hs8_71151000": 0,
        "hs8_71161025": -9456,
        "hs8_71162005": -1700176,
        "hs8_71162015": -506060,
        "hs8_71162030": -37425,
        "hs8_71162035": -40409,
        "hs8_71162040": -155536,
        "hs8_71162050": -1975830,
        "hs8_71171100": 6969,
        "hs8_71171915": -4302,
        "hs8_71171920": 0,
        "hs8_71171930": -9622,
        "hs8_71171990": 1224596,
        "hs8_71179010": 1110000,
        "hs8_71179030": -47909,
        "hs8_71179055": -2234,
        "hs8_71179075": -133275,
        "hs8_71179090": 6625094,
        "hs8_71181000": -307696,
        "hs8_71189000": 1916214
      },
      {
        "periodKey": "2024-09",
        "periodLabel": "Sep 2024",
        "periodSort": 202409,
        "hs8_71012100": 530000,
        "hs8_71021000": -2277,
        "hs8_71022110": 230000,
        "hs8_71022140": -27575,
        "hs8_71022900": -5665,
        "hs8_71023100": 18540000,
        "hs8_71023900": -507637340,
        "hs8_71031020": -90390,
        "hs8_71031040": -9877,
        "hs8_71039100": -42989442,
        "hs8_71039910": -8020426,
        "hs8_71039950": -250017,
        "hs8_71041000": -3449,
        "hs8_71042100": -120341,
        "hs8_71042900": 20000,
        "hs8_71049110": -77335303,
        "hs8_71049150": -67537,
        "hs8_71049910": -45804,
        "hs8_71049950": -121105,
        "hs8_71051000": -116566,
        "hs8_71059000": 0,
        "hs8_71061000": -311856,
        "hs8_71069110": 0,
        "hs8_71069210": -4063,
        "hs8_71069250": -442132,
        "hs8_71070000": 0,
        "hs8_71081100": 0,
        "hs8_71081210": -3720852,
        "hs8_71081310": 0,
        "hs8_71090000": 10000,
        "hs8_71101100": -5017324,
        "hs8_71101900": 170000,
        "hs8_71102100": 0,
        "hs8_71102900": 0,
        "hs8_71103100": 7746058,
        "hs8_71103900": 350000,
        "hs8_71104100": 0,
        "hs8_71104900": 130000,
        "hs8_71110000": 0,
        "hs8_71129201": -610119,
        "hs8_71129901": -396125,
        "hs8_71131110": -66599,
        "hs8_71131120": -193691,
        "hs8_71131150": -42828011,
        "hs8_71131910": -87411,
        "hs8_71131921": 154851,
        "hs8_71131925": -791606,
        "hs8_71131929": -30355318,
        "hs8_71131930": -46836,
        "hs8_71131950": -303390630,
        "hs8_71132050": -34712,
        "hs8_71141110": 1330000,
        "hs8_71141120": 0,
        "hs8_71141160": -17677,
        "hs8_71141170": -243926,
        "hs8_71142000": -17528,
        "hs8_71151000": 0,
        "hs8_71159040": -20385,
        "hs8_71159060": -17003,
        "hs8_71161010": -8700,
        "hs8_71161025": -4200,
        "hs8_71162005": -2927890,
        "hs8_71162015": -237280,
        "hs8_71162030": -56265,
        "hs8_71162035": -74200,
        "hs8_71162040": -155291,
        "hs8_71162050": -2731416,
        "hs8_71171100": 26320,
        "hs8_71171920": 50000,
        "hs8_71171930": -16097,
        "hs8_71171990": 1185690,
        "hs8_71179010": 1792145,
        "hs8_71179020": -4410,
        "hs8_71179030": -79115,
        "hs8_71179055": -19147,
        "hs8_71179060": -5209,
        "hs8_71179075": -171236,
        "hs8_71179090": 6563602,
        "hs8_71181000": 292678,
        "hs8_71189000": -147420
      },
      {
        "periodKey": "2024-10",
        "periodLabel": "Oct 2024",
        "periodSort": 202410,
        "hs8_71011060": -7182,
        "hs8_71012100": 0,
        "hs8_71012260": -15000,
        "hs8_71021000": 0,
        "hs8_71022110": 510000,
        "hs8_71022900": -22469,
        "hs8_71023100": 18480000,
        "hs8_71023900": -638286969,
        "hs8_71031020": -225113,
        "hs8_71031040": -6847,
        "hs8_71039100": -7556791,
        "hs8_71039910": -6563652,
        "hs8_71039950": -159114,
        "hs8_71041000": 0,
        "hs8_71042100": -173778,
        "hs8_71042900": 63,
        "hs8_71049110": -94181030,
        "hs8_71049150": -184801,
        "hs8_71049910": -127685,
        "hs8_71049950": -5233,
        "hs8_71051000": -116937,
        "hs8_71059000": 0,
        "hs8_71061000": -26626,
        "hs8_71069110": 0,
        "hs8_71069210": 10000,
        "hs8_71069250": -496250,
        "hs8_71070000": 60000,
        "hs8_71081100": -19570,
        "hs8_71081210": 0,
        "hs8_71081310": 0,
        "hs8_71090000": 0,
        "hs8_71101900": 910000,
        "hs8_71102100": 0,
        "hs8_71102900": 500000,
        "hs8_71103100": 0,
        "hs8_71103900": 0,
        "hs8_71104100": 130000,
        "hs8_71104900": 0,
        "hs8_71110000": 0,
        "hs8_71129201": -1443206,
        "hs8_71131110": -8741,
        "hs8_71131120": -361027,
        "hs8_71131150": -46969762,
        "hs8_71131910": -124484,
        "hs8_71131921": 1012183,
        "hs8_71131925": -570862,
        "hs8_71131929": -39701140,
        "hs8_71131930": -549622,
        "hs8_71131950": -368647870,
        "hs8_71132029": -9886,
        "hs8_71132050": -98352,
        "hs8_71141110": 3266308,
        "hs8_71141120": 0,
        "hs8_71141130": -2134,
        "hs8_71141140": -2756,
        "hs8_71141150": -83504,
        "hs8_71141160": -20534,
        "hs8_71141170": -774829,
        "hs8_71141900": -131343,
        "hs8_71142000": -67156,
        "hs8_71151000": 320000,
        "hs8_71159005": -124876,
        "hs8_71161025": -3360,
        "hs8_71162005": -2162887,
        "hs8_71162015": -356590,
        "hs8_71162030": -12721,
        "hs8_71162035": -19373,
        "hs8_71162040": -354136,
        "hs8_71162050": -3239802,
        "hs8_71171100": 25512,
        "hs8_71171905": -6813,
        "hs8_71171915": -5209,
        "hs8_71171920": 10000,
        "hs8_71171930": -18805,
        "hs8_71171990": 758582,
        "hs8_71179010": 670000,
        "hs8_71179030": -114840,
        "hs8_71179075": -140236,
        "hs8_71179090": 7251824,
        "hs8_71181000": 914839,
        "hs8_71189000": -3743646
      },
      {
        "periodKey": "2024-11",
        "periodLabel": "Nov 2024",
        "periodSort": 202411,
        "hs8_71011030": -42199,
        "hs8_71012100": 0,
        "hs8_71021000": 0,
        "hs8_71022110": 190000,
        "hs8_71022140": -32000,
        "hs8_71023100": 11900000,
        "hs8_71023900": -333473232,
        "hs8_71031020": -235923,
        "hs8_71031040": -41443,
        "hs8_71039100": -10050282,
        "hs8_71039910": -3368278,
        "hs8_71039950": -116268,
        "hs8_71041000": -5556,
        "hs8_71042100": -72527,
        "hs8_71042900": -13870,
        "hs8_71049110": -49626101,
        "hs8_71049150": -179867,
        "hs8_71049910": -450197,
        "hs8_71051000": -20115,
        "hs8_71059000": 0,
        "hs8_71061000": 314928,
        "hs8_71069110": 0,
        "hs8_71069210": -19646,
        "hs8_71069250": -296258,
        "hs8_71070000": 3124,
        "hs8_71081100": 0,
        "hs8_71081210": 0,
        "hs8_71081310": 0,
        "hs8_71090000": 0,
        "hs8_71101900": 230000,
        "hs8_71102100": 0,
        "hs8_71102900": 0,
        "hs8_71103100": 0,
        "hs8_71103900": 0,
        "hs8_71104100": 0,
        "hs8_71104900": 0,
        "hs8_71110000": 0,
        "hs8_71129201": -156830,
        "hs8_71131110": -162895,
        "hs8_71131120": -270830,
        "hs8_71131150": -35928218,
        "hs8_71131910": -239865,
        "hs8_71131921": 19303,
        "hs8_71131925": -371332,
        "hs8_71131929": -26908809,
        "hs8_71131930": -81463,
        "hs8_71131950": -239607741,
        "hs8_71132029": -10677,
        "hs8_71132050": -135032,
        "hs8_71141110": 700000,
        "hs8_71141120": 0,
        "hs8_71141150": -2315,
        "hs8_71141160": -20178,
        "hs8_71141170": -269425,
        "hs8_71142000": -25294,
        "hs8_71151000": 0,
        "hs8_71159060": -3328,
        "hs8_71161025": -3137,
        "hs8_71162005": -2860954,
        "hs8_71162015": -367638,
        "hs8_71162035": -12223,
        "hs8_71162040": -269357,
        "hs8_71162050": -1922346,
        "hs8_71171100": 30000,
        "hs8_71171905": -3563,
        "hs8_71171920": 0,
        "hs8_71171930": -2413,
        "hs8_71171990": 1109861,
        "hs8_71179010": 1567659,
        "hs8_71179020": -15555,
        "hs8_71179030": -64780,
        "hs8_71179055": -10107,
        "hs8_71179075": -109128,
        "hs8_71179090": 6376782,
        "hs8_71181000": -73455,
        "hs8_71189000": 100000
      },
      {
        "periodKey": "2024-12",
        "periodLabel": "Dec 2024",
        "periodSort": 202412,
        "hs8_71011030": -30000,
        "hs8_71012100": 0,
        "hs8_71012230": -10000,
        "hs8_71012260": -16429,
        "hs8_71021000": 0,
        "hs8_71022110": 260000,
        "hs8_71022130": -9070,
        "hs8_71022140": -3726,
        "hs8_71022900": -93889,
        "hs8_71023100": 27220000,
        "hs8_71023900": -487195451,
        "hs8_71031020": -191984,
        "hs8_71031040": -6320,
        "hs8_71039100": -21455425,
        "hs8_71039910": -10124638,
        "hs8_71039950": -155572,
        "hs8_71041000": 0,
        "hs8_71042100": -134139,
        "hs8_71042900": -13794,
        "hs8_71049110": -71775668,
        "hs8_71049150": -208569,
        "hs8_71049910": -864231,
        "hs8_71051000": -78358,
        "hs8_71059000": 0,
        "hs8_71061000": -346200,
        "hs8_71069110": 0,
        "hs8_71069210": 90415,
        "hs8_71069250": -546674,
        "hs8_71070000": -9471,
        "hs8_71081100": 0,
        "hs8_71081210": 0,
        "hs8_71081310": 0,
        "hs8_71090000": 0,
        "hs8_71101900": 2570000,
        "hs8_71102100": 380000,
        "hs8_71102900": 270000,
        "hs8_71103100": 0,
        "hs8_71103900": 170000,
        "hs8_71104100": 0,
        "hs8_71104900": 0,
        "hs8_71110000": 0,
        "hs8_71129901": -420125,
        "hs8_71131110": -144815,
        "hs8_71131120": -216724,
        "hs8_71131150": -33244270,
        "hs8_71131910": -290009,
        "hs8_71131921": -181079,
        "hs8_71131925": -608663,
        "hs8_71131929": -26290338,
        "hs8_71131930": -68100,
        "hs8_71131950": -256078111,
        "hs8_71132021": -3994,
        "hs8_71132029": -4819,
        "hs8_71132050": -155120,
        "hs8_71141110": 1020000,
        "hs8_71141120": 0,
        "hs8_71141150": -7622,
        "hs8_71141170": -214332,
        "hs8_71142000": -6581,
        "hs8_71151000": 0,
        "hs8_71159060": -11220,
        "hs8_71162005": -1409925,
        "hs8_71162015": -98886,
        "hs8_71162030": -30076,
        "hs8_71162035": -8322,
        "hs8_71162040": -184323,
        "hs8_71162050": -2524814,
        "hs8_71171100": 1278,
        "hs8_71171915": -5083,
        "hs8_71171920": 10000,
        "hs8_71171960": -5653,
        "hs8_71171990": 623360,
        "hs8_71179010": 870000,
        "hs8_71179020": -4643,
        "hs8_71179030": -50576,
        "hs8_71179060": -46287,
        "hs8_71179075": -112002,
        "hs8_71179090": 7417558,
        "hs8_71181000": -50048,
        "hs8_71189000": 145352
      },
      {
        "periodKey": "2025-01",
        "periodLabel": "Jan 2025",
        "periodSort": 202501,
        "hs8_71011060": -6991,
        "hs8_71012100": 0,
        "hs8_71012230": -11703,
        "hs8_71021000": 0,
        "hs8_71022110": 240000,
        "hs8_71022140": -40633,
        "hs8_71022900": -48082,
        "hs8_71023100": 40233200,
        "hs8_71023900": -549779925,
        "hs8_71031020": -634039,
        "hs8_71031040": -55969,
        "hs8_71039100": -41513728,
        "hs8_71039910": -24987130,
        "hs8_71039950": -215109,
        "hs8_71041000": -4977,
        "hs8_71042100": -43207,
        "hs8_71042900": 10000,
        "hs8_71049110": -62528933,
        "hs8_71049150": -229776,
        "hs8_71049910": -155754,
        "hs8_71051000": -55908,
        "hs8_71059000": 0,
        "hs8_71061000": 290000,
        "hs8_71069110": 0,
        "hs8_71069210": 50000,
        "hs8_71069250": -408008,
        "hs8_71070000": -3464,
        "hs8_71081100": 0,
        "hs8_71081210": 0,
        "hs8_71081310": 0,
        "hs8_71090000": 0,
        "hs8_71101100": -1966769,
        "hs8_71101900": 700000,
        "hs8_71102100": 2780000,
        "hs8_71102900": 160000,
        "hs8_71103100": -27594992,
        "hs8_71103900": 200000,
        "hs8_71104100": 0,
        "hs8_71104900": 0,
        "hs8_71110000": 0,
        "hs8_71129201": -720788,
        "hs8_71129901": -742537,
        "hs8_71131110": -142894,
        "hs8_71131120": -377700,
        "hs8_71131150": -29115527,
        "hs8_71131910": -154077,
        "hs8_71131921": 668128,
        "hs8_71131925": -315058,
        "hs8_71131929": -22444792,
        "hs8_71131930": -128684,
        "hs8_71131950": -200460536,
        "hs8_71132050": -197675,
        "hs8_71141110": 850000,
        "hs8_71141120": 0,
        "hs8_71141150": -23475,
        "hs8_71141170": -125823,
        "hs8_71141900": -4770,
        "hs8_71151000": 0,
        "hs8_71159005": -3303662,
        "hs8_71161010": -3887,
        "hs8_71162005": -1727796,
        "hs8_71162015": -166179,
        "hs8_71162030": -61774,
        "hs8_71162035": -56912,
        "hs8_71162040": -180522,
        "hs8_71162050": -1776963,
        "hs8_71171100": 30000,
        "hs8_71171905": -2848,
        "hs8_71171915": -66700,
        "hs8_71171920": 10000,
        "hs8_71171930": -48948,
        "hs8_71171990": 961040.9999999998,
        "hs8_71179010": 1025832,
        "hs8_71179020": -2332,
        "hs8_71179030": -104917,
        "hs8_71179055": -59925,
        "hs8_71179075": -151314,
        "hs8_71179090": 7776289.999999999,
        "hs8_71181000": -21737,
        "hs8_71189000": 153509
      },
      {
        "periodKey": "2025-02",
        "periodLabel": "Feb 2025",
        "periodSort": 202502,
        "hs8_71011060": -6760,
        "hs8_71012100": 460000,
        "hs8_71021000": 0,
        "hs8_71022110": 220000,
        "hs8_71022140": -16750,
        "hs8_71022900": -28145,
        "hs8_71023100": 37510000,
        "hs8_71023900": -471050289,
        "hs8_71031020": -27086,
        "hs8_71031040": -9761,
        "hs8_71039100": -12987111,
        "hs8_71039910": -2987703,
        "hs8_71039950": -184652,
        "hs8_71041000": 0,
        "hs8_71042100": -241202,
        "hs8_71042900": 24930,
        "hs8_71049110": -67600498,
        "hs8_71049150": -153296,
        "hs8_71049910": -86946,
        "hs8_71051000": -40328,
        "hs8_71059000": 0,
        "hs8_71061000": -292545,
        "hs8_71069110": 0,
        "hs8_71069210": -62096,
        "hs8_71069250": -111028,
        "hs8_71070000": 60000,
        "hs8_71081100": 0,
        "hs8_71081210": 0,
        "hs8_71081310": 0,
        "hs8_71090000": 0,
        "hs8_71101900": 1370000,
        "hs8_71102100": 2670000,
        "hs8_71102900": 280000,
        "hs8_71103100": -1182568,
        "hs8_71103900": 210000,
        "hs8_71104100": 80000,
        "hs8_71104900": 0,
        "hs8_71110000": 0,
        "hs8_71129901": -290208,
        "hs8_71131110": -84871,
        "hs8_71131120": -186319,
        "hs8_71131150": -23335653,
        "hs8_71131910": -181055,
        "hs8_71131921": 773153,
        "hs8_71131925": -427714,
        "hs8_71131929": -16033688,
        "hs8_71131930": -51742,
        "hs8_71131950": -186579086,
        "hs8_71132030": -2075,
        "hs8_71132050": -36998,
        "hs8_71141110": 610000,
        "hs8_71141120": 0,
        "hs8_71141150": -8844,
        "hs8_71141160": -13740,
        "hs8_71141170": -85204,
        "hs8_71141900": -24989,
        "hs8_71151000": 160000,
        "hs8_71159005": -532954,
        "hs8_71161025": -17110,
        "hs8_71162005": -1661877,
        "hs8_71162015": -336358,
        "hs8_71162030": -51388,
        "hs8_71162035": -49526,
        "hs8_71162040": -118960,
        "hs8_71162050": -1667795,
        "hs8_71171100": 20000,
        "hs8_71171905": -2230,
        "hs8_71171920": 3216,
        "hs8_71171990": 1399735,
        "hs8_71179010": 710000,
        "hs8_71179030": -86097,
        "hs8_71179055": -3408,
        "hs8_71179075": -69969,
        "hs8_71179090": 7190105,
        "hs8_71181000": 54820,
        "hs8_71189000": 59745
      },
      {
        "periodKey": "2025-03",
        "periodLabel": "Mar 2025",
        "periodSort": 202503,
        "hs8_71012100": 7500,
        "hs8_71012230": -45600,
        "hs8_71012260": -24582,
        "hs8_71021000": 0,
        "hs8_71022110": 386000,
        "hs8_71022130": -3500,
        "hs8_71022140": -3200,
        "hs8_71022900": -32651,
        "hs8_71023100": 68250000,
        "hs8_71023900": -674005277,
        "hs8_71031020": -157877,
        "hs8_71031040": -9004,
        "hs8_71039100": -13044976,
        "hs8_71039910": -7491418,
        "hs8_71039950": -297108,
        "hs8_71041000": 0,
        "hs8_71042100": -123594,
        "hs8_71042900": 241230,
        "hs8_71049110": -97693972,
        "hs8_71049150": -164683,
        "hs8_71049910": -277869,
        "hs8_71051000": -62554,
        "hs8_71059000": 10000,
        "hs8_71061000": 330000,
        "hs8_71069110": -31207967,
        "hs8_71069210": 160000,
        "hs8_71069250": -335630,
        "hs8_71070000": 0,
        "hs8_71081100": 0,
        "hs8_71081210": 0,
        "hs8_71081310": 0,
        "hs8_71090000": 0,
        "hs8_71101900": 1040000,
        "hs8_71102100": 0,
        "hs8_71102900": 320000,
        "hs8_71103100": -8142981,
        "hs8_71103900": 310000,
        "hs8_71104100": -12688,
        "hs8_71104900": 0,
        "hs8_71110000": 0,
        "hs8_71129201": -438177,
        "hs8_71131110": -60105,
        "hs8_71131120": -213056,
        "hs8_71131150": -30564094,
        "hs8_71131910": -226965,
        "hs8_71131921": 792738,
        "hs8_71131925": -1973642,
        "hs8_71131929": -31021445,
        "hs8_71131930": -112747,
        "hs8_71131950": -277331978,
        "hs8_71132050": -31901,
        "hs8_71141110": 1230000,
        "hs8_71141120": 0,
        "hs8_71141130": -3640,
        "hs8_71141150": -6169,
        "hs8_71141160": -8236,
        "hs8_71141170": -225615,
        "hs8_71141900": -14411,
        "hs8_71142000": -40098,
        "hs8_71151000": 0,
        "hs8_71159040": -6752,
        "hs8_71161025": -22680,
        "hs8_71162005": -2036344,
        "hs8_71162015": -360624,
        "hs8_71162030": -9023,
        "hs8_71162035": -32787,
        "hs8_71162040": -192257,
        "hs8_71162050": -1672912,
        "hs8_71171100": 17425,
        "hs8_71171915": -21498,
        "hs8_71171920": -3276,
        "hs8_71171990": 1928524,
        "hs8_71179010": 820000,
        "hs8_71179020": -8346,
        "hs8_71179030": -162475,
        "hs8_71179075": -75639,
        "hs8_71179090": 7921937,
        "hs8_71181000": -46550,
        "hs8_71189000": 126211
      },
      {
        "periodKey": "2025-04",
        "periodLabel": "Apr 2025",
        "periodSort": 202504,
        "hs8_71012100": 0,
        "hs8_71012260": -7929,
        "hs8_71021000": 0,
        "hs8_71022110": 550000,
        "hs8_71022140": -9600,
        "hs8_71022900": -25258,
        "hs8_71023100": 38173200,
        "hs8_71023900": -473808965,
        "hs8_71031020": -157449,
        "hs8_71031040": -16484,
        "hs8_71039100": -4380542,
        "hs8_71039910": -2331206,
        "hs8_71039950": -179194,
        "hs8_71041000": 0,
        "hs8_71042100": -92861,
        "hs8_71042900": 0,
        "hs8_71049110": -76177116,
        "hs8_71049150": -249033,
        "hs8_71049910": -343785,
        "hs8_71049950": -20822,
        "hs8_71051000": -105385,
        "hs8_71059000": 0,
        "hs8_71061000": -335328,
        "hs8_71069110": 120000,
        "hs8_71069210": 70000,
        "hs8_71069250": -577420,
        "hs8_71070000": 0,
        "hs8_71081100": 0,
        "hs8_71081210": -50508,
        "hs8_71081310": 60000,
        "hs8_71090000": 0,
        "hs8_71101100": -898213,
        "hs8_71101900": 0,
        "hs8_71102100": 0,
        "hs8_71102900": 400000,
        "hs8_71103100": 0,
        "hs8_71103900": 190000,
        "hs8_71104100": 90000,
        "hs8_71104900": 130000,
        "hs8_71110000": 0,
        "hs8_71131110": -86586,
        "hs8_71131120": -166671,
        "hs8_71131150": -28267135,
        "hs8_71131910": -168476,
        "hs8_71131921": 782704,
        "hs8_71131925": -187921,
        "hs8_71131929": -22335388,
        "hs8_71131930": -387692,
        "hs8_71131950": -202253032,
        "hs8_71132050": -140679,
        "hs8_71141110": 1380000,
        "hs8_71141120": 0,
        "hs8_71141130": -3945,
        "hs8_71141140": -5099,
        "hs8_71141150": -22262,
        "hs8_71141160": -17098,
        "hs8_71141170": -469281,
        "hs8_71141900": -39079,
        "hs8_71151000": 0,
        "hs8_71159040": -42535,
        "hs8_71159060": -2220,
        "hs8_71161010": -4652,
        "hs8_71161025": -31388,
        "hs8_71162005": -1780802,
        "hs8_71162015": -239498,
        "hs8_71162030": -53714,
        "hs8_71162035": -20102,
        "hs8_71162040": -136912,
        "hs8_71162050": -1688193,
        "hs8_71171100": -9656,
        "hs8_71171915": -17066,
        "hs8_71171920": -4948,
        "hs8_71171930": -5650,
        "hs8_71171990": 1023253,
        "hs8_71179010": 870000,
        "hs8_71179020": -60057,
        "hs8_71179030": -233265,
        "hs8_71179075": -293774,
        "hs8_71179090": 5991788,
        "hs8_71181000": 119036,
        "hs8_71189000": 207042
      },
      {
        "periodKey": "2025-05",
        "periodLabel": "May 2025",
        "periodSort": 202505,
        "hs8_71011060": -6882,
        "hs8_71012100": 0,
        "hs8_71012230": -8567,
        "hs8_71021000": 16770,
        "hs8_71022110": 330000,
        "hs8_71022140": -25500,
        "hs8_71023100": 24480000,
        "hs8_71023900": -208972688,
        "hs8_71031020": -68237,
        "hs8_71031040": -28676,
        "hs8_71039100": -1523439,
        "hs8_71039910": -3250456,
        "hs8_71039950": -166209,
        "hs8_71041000": -9609,
        "hs8_71042100": -29986,
        "hs8_71042900": 194930,
        "hs8_71049110": -33970741,
        "hs8_71049150": -67248,
        "hs8_71049910": -69484,
        "hs8_71049950": -33013,
        "hs8_71051000": -84807,
        "hs8_71059000": 0,
        "hs8_71061000": 0,
        "hs8_71069110": 0,
        "hs8_71069210": 0,
        "hs8_71069250": -538785,
        "hs8_71070000": 100000,
        "hs8_71081100": 0,
        "hs8_71081210": 0,
        "hs8_71081310": 63370000,
        "hs8_71090000": 0,
        "hs8_71101100": -1909752,
        "hs8_71101900": 0,
        "hs8_71102100": 50000,
        "hs8_71102900": 90000,
        "hs8_71103100": -10905379,
        "hs8_71103900": 130000,
        "hs8_71104100": 100000,
        "hs8_71104900": 200000,
        "hs8_71110000": 0,
        "hs8_71123001": -390822,
        "hs8_71129201": -436915,
        "hs8_71131110": -22656,
        "hs8_71131120": -316560,
        "hs8_71131150": -25929133,
        "hs8_71131910": -248304,
        "hs8_71131921": 1379364,
        "hs8_71131925": -416688,
        "hs8_71131929": -16025897,
        "hs8_71131930": -54596,
        "hs8_71131950": -167590838,
        "hs8_71132030": -6879,
        "hs8_71132050": -363237,
        "hs8_71141110": 1250000,
        "hs8_71141120": 0,
        "hs8_71141150": -74548,
        "hs8_71141170": -355634,
        "hs8_71141900": -22183,
        "hs8_71142000": -7692,
        "hs8_71151000": 0,
        "hs8_71159005": -28155,
        "hs8_71161025": -14591,
        "hs8_71162005": -2223882,
        "hs8_71162015": -316166,
        "hs8_71162030": -23337,
        "hs8_71162035": -6105,
        "hs8_71162040": -110709,
        "hs8_71162050": -2162477,
        "hs8_71171100": -913,
        "hs8_71171920": -6104,
        "hs8_71171990": 1467452,
        "hs8_71179010": 711797,
        "hs8_71179020": -32760,
        "hs8_71179030": -108712,
        "hs8_71179060": -6372,
        "hs8_71179075": -173293,
        "hs8_71179090": 7630907.000000001,
        "hs8_71181000": -15198,
        "hs8_71189000": 59317
      },
      {
        "periodKey": "2025-06",
        "periodLabel": "Jun 2025",
        "periodSort": 202506,
        "hs8_71012100": 20000,
        "hs8_71012260": -2320,
        "hs8_71021000": 0,
        "hs8_71022110": 190000,
        "hs8_71022140": -27000,
        "hs8_71023100": 15480000,
        "hs8_71023900": -143493685,
        "hs8_71031020": -199343,
        "hs8_71039100": -1199492,
        "hs8_71039910": -1397007,
        "hs8_71039950": -39401,
        "hs8_71041000": 0,
        "hs8_71042100": -50421,
        "hs8_71042900": -5070,
        "hs8_71049110": -29991195,
        "hs8_71049150": -86555,
        "hs8_71049910": -154420,
        "hs8_71049950": -16227,
        "hs8_71051000": -40146,
        "hs8_71059000": 0,
        "hs8_71061000": 0,
        "hs8_71069110": 70000,
        "hs8_71069210": 60000,
        "hs8_71069250": -539647,
        "hs8_71070000": 106953,
        "hs8_71081100": 0,
        "hs8_71081210": 30000,
        "hs8_71081310": 0,
        "hs8_71090000": 0,
        "hs8_71101900": 0,
        "hs8_71102100": 0,
        "hs8_71102900": 53759,
        "hs8_71103100": 0,
        "hs8_71103900": 100000,
        "hs8_71104100": 110000,
        "hs8_71104900": 0,
        "hs8_71110000": 0,
        "hs8_71129201": -1072524,
        "hs8_71129901": -76599,
        "hs8_71131110": -89145,
        "hs8_71131120": -122620,
        "hs8_71131150": -21971291,
        "hs8_71131910": -147443,
        "hs8_71131921": 1512068,
        "hs8_71131925": -156428,
        "hs8_71131929": -12658268,
        "hs8_71131930": -192837,
        "hs8_71131950": -142999622,
        "hs8_71132050": -28765,
        "hs8_71141110": 850000,
        "hs8_71141120": 0,
        "hs8_71141140": -15286,
        "hs8_71141170": -344233,
        "hs8_71141900": -5364,
        "hs8_71142000": -38274,
        "hs8_71151000": 0,
        "hs8_71159005": -41649,
        "hs8_71159060": -42202,
        "hs8_71161010": -2278,
        "hs8_71162005": -1441915,
        "hs8_71162015": -166091,
        "hs8_71162030": -34074,
        "hs8_71162035": -14474,
        "hs8_71162040": -82717,
        "hs8_71162050": -1833542,
        "hs8_71171100": -10258,
        "hs8_71171915": -2182,
        "hs8_71171920": 3585,
        "hs8_71171930": -4276,
        "hs8_71171990": 1104160,
        "hs8_71179010": 547792,
        "hs8_71179020": -14785,
        "hs8_71179030": -122825,
        "hs8_71179055": -10761,
        "hs8_71179075": -51401,
        "hs8_71179090": 6345642,
        "hs8_71181000": 14239,
        "hs8_71189000": 63830
      },
      {
        "periodKey": "2025-07",
        "periodLabel": "Jul 2025",
        "periodSort": 202507,
        "hs8_71012100": 0,
        "hs8_71012260": -20926,
        "hs8_71021000": 0,
        "hs8_71022110": 190000,
        "hs8_71022130": -2000,
        "hs8_71022140": -2500,
        "hs8_71022900": -26438,
        "hs8_71023100": 28310000,
        "hs8_71023900": -287267236,
        "hs8_71031020": -116297,
        "hs8_71031040": -12900,
        "hs8_71039100": -1604659,
        "hs8_71039910": -1812189,
        "hs8_71039950": -73263,
        "hs8_71041000": -29619,
        "hs8_71042100": -118111,
        "hs8_71042900": 16000,
        "hs8_71049110": -63824820,
        "hs8_71049150": -168651,
        "hs8_71049910": -551865,
        "hs8_71049950": -28894,
        "hs8_71051000": -26731,
        "hs8_71059000": 0,
        "hs8_71061000": 0,
        "hs8_71069110": -122225,
        "hs8_71069210": 70000,
        "hs8_71069250": -367022,
        "hs8_71070000": 0,
        "hs8_71081100": 0,
        "hs8_71081210": 0,
        "hs8_71081310": 0,
        "hs8_71090000": 0,
        "hs8_71101900": -9375151,
        "hs8_71102100": 0,
        "hs8_71102900": 244613,
        "hs8_71103100": 0,
        "hs8_71103900": 0,
        "hs8_71104100": 0,
        "hs8_71104900": 270000,
        "hs8_71110000": 0,
        "hs8_71129201": -622508,
        "hs8_71131110": -63568,
        "hs8_71131120": -162965,
        "hs8_71131150": -30700970,
        "hs8_71131910": -298373,
        "hs8_71131921": 1294591,
        "hs8_71131925": -121750,
        "hs8_71131929": -21947458,
        "hs8_71131930": -48893,
        "hs8_71131950": -248993149,
        "hs8_71132029": -2348,
        "hs8_71132030": -34067,
        "hs8_71132050": -72836,
        "hs8_71141110": 2770000,
        "hs8_71141120": 0,
        "hs8_71141140": -21749,
        "hs8_71141150": -50605,
        "hs8_71141170": -447607,
        "hs8_71141900": -45216,
        "hs8_71142000": -97879,
        "hs8_71151000": 50000,
        "hs8_71159005": -12531,
        "hs8_71159040": -3654,
        "hs8_71159060": -14612,
        "hs8_71161025": -8044,
        "hs8_71162005": -2378430,
        "hs8_71162015": -600077,
        "hs8_71162030": -110237,
        "hs8_71162035": -2400,
        "hs8_71162040": -234134,
        "hs8_71162050": -1891241,
        "hs8_71171100": 513,
        "hs8_71171915": -20565,
        "hs8_71171920": 27710,
        "hs8_71171990": 1116951,
        "hs8_71179010": 496872,
        "hs8_71179030": -11970,
        "hs8_71179055": -11133,
        "hs8_71179075": -60714,
        "hs8_71179090": 7321823,
        "hs8_71181000": 553583,
        "hs8_71189000": -342271
      },
      {
        "periodKey": "2025-08",
        "periodLabel": "Aug 2025",
        "periodSort": 202508,
        "hs8_71012100": 0,
        "hs8_71012260": -3764,
        "hs8_71021000": 0,
        "hs8_71022110": 850000,
        "hs8_71022140": -8500,
        "hs8_71023100": 37690000,
        "hs8_71023900": -208689024,
        "hs8_71031020": -101685,
        "hs8_71031040": -31228,
        "hs8_71039100": -803506,
        "hs8_71039910": -1253948,
        "hs8_71039950": -76150,
        "hs8_71041000": 0,
        "hs8_71042100": -25256,
        "hs8_71042900": 112062,
        "hs8_71049110": -50460792,
        "hs8_71049150": -176394,
        "hs8_71049910": -201731,
        "hs8_71049950": -41700,
        "hs8_71051000": -97519,
        "hs8_71059000": 0,
        "hs8_71061000": 0,
        "hs8_71069110": 0,
        "hs8_71069210": 449867,
        "hs8_71069250": -614017,
        "hs8_71070000": 0,
        "hs8_71081100": 0,
        "hs8_71081210": 140000,
        "hs8_71081310": 0,
        "hs8_71090000": 0,
        "hs8_71101900": 0,
        "hs8_71102100": 110000,
        "hs8_71102900": 2435,
        "hs8_71103100": 0,
        "hs8_71103900": 110000,
        "hs8_71104100": 70000,
        "hs8_71104900": 0,
        "hs8_71110000": 0,
        "hs8_71129201": -312545,
        "hs8_71131110": -73152,
        "hs8_71131120": -155074,
        "hs8_71131150": -29303401,
        "hs8_71131910": -253004,
        "hs8_71131921": 1036070,
        "hs8_71131925": -6387,
        "hs8_71131929": -17043456,
        "hs8_71131930": -45215,
        "hs8_71131950": -160293550,
        "hs8_71132050": -3582240,
        "hs8_71141110": 2124020,
        "hs8_71141120": 20000,
        "hs8_71141140": -15956,
        "hs8_71141150": -41045,
        "hs8_71141160": -13928,
        "hs8_71141170": -645349,
        "hs8_71141900": -15356,
        "hs8_71151000": 110000,
        "hs8_71159040": -41540,
        "hs8_71161010": -3248,
        "hs8_71162005": -2044567,
        "hs8_71162015": -1190722,
        "hs8_71162030": -9748,
        "hs8_71162035": -37615,
        "hs8_71162040": -187336,
        "hs8_71162050": -2098581,
        "hs8_71171100": 30000,
        "hs8_71171905": -2556,
        "hs8_71171915": -3004,
        "hs8_71171920": -2466,
        "hs8_71171930": -7198,
        "hs8_71171990": 1418455,
        "hs8_71179010": 637800,
        "hs8_71179020": -6146,
        "hs8_71179030": -63111,
        "hs8_71179055": -3051,
        "hs8_71179075": -63451,
        "hs8_71179090": 6428811,
        "hs8_71181000": 160161,
        "hs8_71189000": 107439
      },
      {
        "periodKey": "2025-09",
        "periodLabel": "Sep 2025",
        "periodSort": 202509,
        "hs8_71012100": 440000,
        "hs8_71012260": -3000,
        "hs8_71021000": 0,
        "hs8_71022110": 160000,
        "hs8_71022140": -3800,
        "hs8_71023100": 31150000,
        "hs8_71023900": -89647761,
        "hs8_71031020": -29699,
        "hs8_71039100": -117290,
        "hs8_71039910": -368000,
        "hs8_71039950": -43979,
        "hs8_71041000": -13717,
        "hs8_71042900": 100000,
        "hs8_71049110": -3899461,
        "hs8_71049150": -25903,
        "hs8_71049910": -59052,
        "hs8_71049950": -43948,
        "hs8_71051000": -12120,
        "hs8_71059000": 10000,
        "hs8_71061000": 0,
        "hs8_71069110": 50000,
        "hs8_71069210": 16403,
        "hs8_71069250": -192843,
        "hs8_71070000": 70000,
        "hs8_71081100": 0,
        "hs8_71081210": 70000,
        "hs8_71081310": 0,
        "hs8_71090000": 0,
        "hs8_71101100": -35833809,
        "hs8_71101900": 0,
        "hs8_71102100": 0,
        "hs8_71102900": 3930000,
        "hs8_71103100": 0,
        "hs8_71103900": 200000,
        "hs8_71104100": -33748,
        "hs8_71104900": 0,
        "hs8_71110000": 0,
        "hs8_71129201": -6398,
        "hs8_71131110": 97310,
        "hs8_71131120": -52821,
        "hs8_71131150": -7440726,
        "hs8_71131910": -99849,
        "hs8_71131921": 1935809,
        "hs8_71131925": 306375,
        "hs8_71131929": -895238,
        "hs8_71131930": -13574,
        "hs8_71131950": -22646671,
        "hs8_71132050": -1103644,
        "hs8_71141110": 1610000,
        "hs8_71141120": 0,
        "hs8_71141170": -71487,
        "hs8_71142000": -24284,
        "hs8_71151000": 0,
        "hs8_71159060": -3360,
        "hs8_71161025": -5298,
        "hs8_71162005": -2116798,
        "hs8_71162015": -323577,
        "hs8_71162030": -11600,
        "hs8_71162035": -17704,
        "hs8_71162040": -100104,
        "hs8_71162050": -1754949,
        "hs8_71171100": 10000,
        "hs8_71171905": -13399,
        "hs8_71171915": -22991,
        "hs8_71171920": 30000,
        "hs8_71171990": 1187226,
        "hs8_71179010": 647975,
        "hs8_71179020": -22003,
        "hs8_71179030": -5691,
        "hs8_71179075": -63929,
        "hs8_71179090": 5361632,
        "hs8_71181000": 700739,
        "hs8_71189000": -85994
      },
      {
        "periodKey": "2025-10",
        "periodLabel": "Oct 2025",
        "periodSort": 202510,
        "hs8_71012100": 0,
        "hs8_71021000": 60000,
        "hs8_71022110": 350000,
        "hs8_71023100": 23610000,
        "hs8_71023900": -135570194,
        "hs8_71031020": -34291,
        "hs8_71039100": -284632,
        "hs8_71039910": -383931,
        "hs8_71039950": -40702,
        "hs8_71041000": 0,
        "hs8_71042100": -35770,
        "hs8_71042900": 0,
        "hs8_71049110": -4671191,
        "hs8_71049150": -70454,
        "hs8_71049910": -4879,
        "hs8_71049950": -3274,
        "hs8_71051000": -33078,
        "hs8_71059000": 0,
        "hs8_71061000": -5266,
        "hs8_71069110": 0,
        "hs8_71069210": -8761,
        "hs8_71069250": -577480,
        "hs8_71070000": 0,
        "hs8_71081100": 0,
        "hs8_71081210": 0,
        "hs8_71081310": 0,
        "hs8_71090000": 0,
        "hs8_71101100": -1972256,
        "hs8_71101900": 0,
        "hs8_71102100": 0,
        "hs8_71102900": 0,
        "hs8_71103100": 0,
        "hs8_71103900": 100000,
        "hs8_71104100": 90000,
        "hs8_71104900": 10000,
        "hs8_71110000": 0,
        "hs8_71129201": -1778316,
        "hs8_71131110": -17514,
        "hs8_71131120": -101171,
        "hs8_71131150": -15539063,
        "hs8_71131910": -35638,
        "hs8_71131921": 2036871,
        "hs8_71131925": 117502,
        "hs8_71131929": -1395567,
        "hs8_71131930": -13948,
        "hs8_71131950": -33187156,
        "hs8_71132010": -2400,
        "hs8_71132030": -15163,
        "hs8_71132050": -233019,
        "hs8_71141110": 2830000,
        "hs8_71141120": 0,
        "hs8_71141160": -7874,
        "hs8_71141170": -103389,
        "hs8_71141900": -2641,
        "hs8_71142000": -28249,
        "hs8_71151000": 0,
        "hs8_71159040": -22753,
        "hs8_71161025": -2477,
        "hs8_71162005": -2553730,
        "hs8_71162015": -682326,
        "hs8_71162030": -33320,
        "hs8_71162040": -254836,
        "hs8_71162050": -1713080,
        "hs8_71171100": 10000,
        "hs8_71171905": -25028,
        "hs8_71171915": -2213,
        "hs8_71171920": 0,
        "hs8_71171930": -28422,
        "hs8_71171960": -3046,
        "hs8_71171990": 1505551.9999999998,
        "hs8_71179010": 580000,
        "hs8_71179020": -16813,
        "hs8_71179030": -39752,
        "hs8_71179055": -8492,
        "hs8_71179075": -20957,
        "hs8_71179090": 6912554,
        "hs8_71181000": 949993,
        "hs8_71189000": -63509
      },
      {
        "periodKey": "2025-11",
        "periodLabel": "Nov 2025",
        "periodSort": 202511,
        "hs8_71012100": 0,
        "hs8_71012260": -4750,
        "hs8_71021000": 0,
        "hs8_71022110": 320000,
        "hs8_71023100": 25540000,
        "hs8_71023900": -56591667,
        "hs8_71031040": -3212,
        "hs8_71039100": -165907,
        "hs8_71039910": -405332,
        "hs8_71039950": -71398,
        "hs8_71041000": -9681,
        "hs8_71042100": -16672,
        "hs8_71042900": 0,
        "hs8_71049110": -4112679,
        "hs8_71049150": -42937,
        "hs8_71049910": -12000,
        "hs8_71049950": -20812,
        "hs8_71051000": -22701,
        "hs8_71059000": 0,
        "hs8_71061000": 0,
        "hs8_71069110": 0,
        "hs8_71069210": 1090000,
        "hs8_71069250": -189256,
        "hs8_71070000": 110000,
        "hs8_71081100": 0,
        "hs8_71081210": 3476097,
        "hs8_71081310": 0,
        "hs8_71090000": 0,
        "hs8_71101900": 0,
        "hs8_71102100": 120000,
        "hs8_71102900": 320000,
        "hs8_71103100": 0,
        "hs8_71103900": 0,
        "hs8_71104100": 0,
        "hs8_71104900": 40000,
        "hs8_71110000": 0,
        "hs8_71129201": -3103,
        "hs8_71131110": -70128,
        "hs8_71131120": -103288,
        "hs8_71131150": -13027357,
        "hs8_71131910": -48574,
        "hs8_71131921": 1657761,
        "hs8_71131925": 271917,
        "hs8_71131929": -803147,
        "hs8_71131930": -21748,
        "hs8_71131950": -33327059,
        "hs8_71132010": -2383,
        "hs8_71132050": -26195,
        "hs8_71141110": 400000,
        "hs8_71141120": 0,
        "hs8_71141145": -3682,
        "hs8_71141170": -59953,
        "hs8_71151000": 0,
        "hs8_71159040": -3905,
        "hs8_71162005": -2402922,
        "hs8_71162015": -595169,
        "hs8_71162035": -6375,
        "hs8_71162040": -62817,
        "hs8_71162050": -1758809,
        "hs8_71171100": 20000,
        "hs8_71171905": -3005,
        "hs8_71171915": -6552,
        "hs8_71171920": 10000,
        "hs8_71171930": -41196,
        "hs8_71171960": -4264,
        "hs8_71171990": 1881749,
        "hs8_71179010": 640000,
        "hs8_71179030": -2455,
        "hs8_71179075": -40508,
        "hs8_71179090": 7028834,
        "hs8_71181000": 1608,
        "hs8_71189000": 41426
      },
      {
        "periodKey": "2025-12",
        "periodLabel": "Dec 2025",
        "periodSort": 202512,
        "hs8_71011060": -3163,
        "hs8_71012100": 0,
        "hs8_71021000": 0,
        "hs8_71022110": 100000,
        "hs8_71023100": 16960000,
        "hs8_71023900": -73514151,
        "hs8_71031040": -18555,
        "hs8_71039100": -60210,
        "hs8_71039910": -479830,
        "hs8_71039950": -76697,
        "hs8_71041000": 0,
        "hs8_71042900": 215200,
        "hs8_71049110": -4420398,
        "hs8_71049150": -105729,
        "hs8_71049910": -19634,
        "hs8_71051000": -4000,
        "hs8_71059000": 0,
        "hs8_71061000": 0,
        "hs8_71069110": 10000,
        "hs8_71069210": -171767,
        "hs8_71070000": 110000,
        "hs8_71081100": 0,
        "hs8_71081210": 34835282,
        "hs8_71081310": 690000,
        "hs8_71081355": -1029602,
        "hs8_71090000": 0,
        "hs8_71101100": -4911272,
        "hs8_71101900": 0,
        "hs8_71102100": 0,
        "hs8_71102900": 137404,
        "hs8_71103100": 0,
        "hs8_71103900": 0,
        "hs8_71104100": -32375,
        "hs8_71104900": 30000,
        "hs8_71110000": 0,
        "hs8_71129201": -10659,
        "hs8_71131110": -159844,
        "hs8_71131120": -105854,
        "hs8_71131150": -13644872,
        "hs8_71131910": -47835,
        "hs8_71131921": 1150719,
        "hs8_71131925": 222021,
        "hs8_71131929": -2077874,
        "hs8_71131930": -21717,
        "hs8_71131950": -31518574,
        "hs8_71132050": -1094902,
        "hs8_71141110": 1040000,
        "hs8_71141120": 0,
        "hs8_71141150": -23426,
        "hs8_71141170": -64352,
        "hs8_71151000": 0,
        "hs8_71161025": -2291,
        "hs8_71162005": -2427017,
        "hs8_71162015": -418413,
        "hs8_71162030": -28237,
        "hs8_71162035": -13608,
        "hs8_71162040": -69448,
        "hs8_71162050": -1772519,
        "hs8_71171100": 10000,
        "hs8_71171905": -6122,
        "hs8_71171915": -39948,
        "hs8_71171920": -2400,
        "hs8_71171930": -2730,
        "hs8_71171960": -2106,
        "hs8_71171990": 879202,
        "hs8_71179010": 595722,
        "hs8_71179020": -8126,
        "hs8_71179030": -7612,
        "hs8_71179075": -98756,
        "hs8_71179090": 7428786,
        "hs8_71181000": 199600,
        "hs8_71189000": 298371
      },
      {
        "periodKey": "2026-01",
        "periodLabel": "Jan 2026",
        "periodSort": 202601,
        "hs8_71012100": 0,
        "hs8_71021000": 0,
        "hs8_71022110": 720000,
        "hs8_71023100": 32780000,
        "hs8_71023900": -113556981,
        "hs8_71031020": -69319,
        "hs8_71031040": -2296,
        "hs8_71039100": -9723219,
        "hs8_71039910": -13850371,
        "hs8_71039950": -63992,
        "hs8_71041000": -7058,
        "hs8_71042100": -3195,
        "hs8_71042900": -6725,
        "hs8_71049110": -2509706,
        "hs8_71049150": -90571,
        "hs8_71049910": -31744,
        "hs8_71051000": -6836,
        "hs8_71059000": 0,
        "hs8_71061000": -5079,
        "hs8_71069110": 50000,
        "hs8_71069210": -106299,
        "hs8_71069250": -160979,
        "hs8_71070000": 0,
        "hs8_71081100": 0,
        "hs8_71081210": 4849871,
        "hs8_71081310": 1970000,
        "hs8_71090000": 0,
        "hs8_71101900": 0,
        "hs8_71102100": 0,
        "hs8_71102900": 140000,
        "hs8_71103100": 0,
        "hs8_71103900": 0,
        "hs8_71104100": 150000,
        "hs8_71104900": 400000,
        "hs8_71110000": 0,
        "hs8_71129201": -1152614,
        "hs8_71131110": -4298,
        "hs8_71131120": -105758,
        "hs8_71131150": -10165831,
        "hs8_71131910": -12557,
        "hs8_71131921": 1529672,
        "hs8_71131925": 12363,
        "hs8_71131929": -1298044,
        "hs8_71131930": -73232,
        "hs8_71131950": -21230541,
        "hs8_71132050": -152068,
        "hs8_71141110": 390000,
        "hs8_71141120": 0,
        "hs8_71141170": -6397,
        "hs8_71141900": -6146,
        "hs8_71151000": 0,
        "hs8_71159005": -4056133,
        "hs8_71162005": -1320750,
        "hs8_71162015": -69648,
        "hs8_71162030": -6725,
        "hs8_71162035": -30528,
        "hs8_71162040": -60353,
        "hs8_71162050": -1978487,
        "hs8_71171100": 17823,
        "hs8_71171905": -3191,
        "hs8_71171920": 10000,
        "hs8_71171930": -10429,
        "hs8_71171990": 2544929,
        "hs8_71179010": 473099,
        "hs8_71179020": -2470,
        "hs8_71179030": -6470,
        "hs8_71179075": -129285,
        "hs8_71179090": 7297903,
        "hs8_71181000": 130000,
        "hs8_71189000": 289480
      },
      {
        "periodKey": "2026-02",
        "periodLabel": "Feb 2026",
        "periodSort": 202602,
        "hs8_71011060": -19679,
        "hs8_71012100": 40000,
        "hs8_71021000": 0,
        "hs8_71022110": 480000,
        "hs8_71022900": -5787,
        "hs8_71023100": 31280000,
        "hs8_71023900": -110471649,
        "hs8_71031020": -28400,
        "hs8_71039100": -738024,
        "hs8_71039910": -795438,
        "hs8_71039950": -110549,
        "hs8_71041000": -2616,
        "hs8_71042100": -9197,
        "hs8_71042900": 40000,
        "hs8_71049110": -12879393,
        "hs8_71049150": -76840,
        "hs8_71049910": -3712613,
        "hs8_71049950": -7037,
        "hs8_71051000": -29683,
        "hs8_71059000": -11300,
        "hs8_71061000": 0,
        "hs8_71069110": 30000,
        "hs8_71069210": 0,
        "hs8_71069250": -109951,
        "hs8_71070000": 150000,
        "hs8_71081100": 0,
        "hs8_71081210": 8050542,
        "hs8_71081310": 1470000,
        "hs8_71090000": 0,
        "hs8_71101100": -822630,
        "hs8_71101900": 0,
        "hs8_71102100": 30000,
        "hs8_71102900": 280000,
        "hs8_71103100": 0,
        "hs8_71103900": 700000,
        "hs8_71104100": -28500,
        "hs8_71104900": 0,
        "hs8_71110000": 0,
        "hs8_71129201": -2721230,
        "hs8_71131110": -137406,
        "hs8_71131120": -112822,
        "hs8_71131150": -10362462,
        "hs8_71131910": -44348,
        "hs8_71131921": 1370838,
        "hs8_71131925": 104398,
        "hs8_71131929": -1074815,
        "hs8_71131930": -4969,
        "hs8_71131950": -18769450,
        "hs8_71132010": -4743,
        "hs8_71132029": -7221,
        "hs8_71132050": -88565,
        "hs8_71141110": 960000,
        "hs8_71141120": 0,
        "hs8_71141170": -6569,
        "hs8_71151000": 0,
        "hs8_71159005": -10677015,
        "hs8_71159030": -2406,
        "hs8_71159040": -17338,
        "hs8_71162005": -1282738,
        "hs8_71162015": -98432,
        "hs8_71162030": -2450,
        "hs8_71162035": -25776,
        "hs8_71162040": -51398,
        "hs8_71162050": -1944309,
        "hs8_71171100": 19490,
        "hs8_71171905": -4226,
        "hs8_71171915": -18752,
        "hs8_71171920": 30000,
        "hs8_71171930": -5716,
        "hs8_71171960": -5772,
        "hs8_71171990": 2086418,
        "hs8_71179010": 659961,
        "hs8_71179030": -11092,
        "hs8_71179075": -175426,
        "hs8_71179090": 7538766,
        "hs8_71181000": 166764,
        "hs8_71189000": 920000
      },
      {
        "periodKey": "2026-03",
        "periodLabel": "Mar 2026",
        "periodSort": 202603,
        "hs8_71012100": 0,
        "hs8_71012260": -2534,
        "hs8_71021000": 0,
        "hs8_71022110": 560000,
        "hs8_71022900": -27664,
        "hs8_71023100": 19640000,
        "hs8_71023900": -152422205,
        "hs8_71031020": -9233,
        "hs8_71039100": -424368,
        "hs8_71039910": -1191242,
        "hs8_71039950": -109979,
        "hs8_71041000": 0,
        "hs8_71042100": -55525,
        "hs8_71042900": 380000,
        "hs8_71049110": -19053928,
        "hs8_71049150": -245013,
        "hs8_71049910": -1468556,
        "hs8_71049950": -15407,
        "hs8_71051000": -14300,
        "hs8_71059000": 0,
        "hs8_71061000": 0,
        "hs8_71069110": 0,
        "hs8_71069210": 7948,
        "hs8_71069250": -88059,
        "hs8_71070000": 0,
        "hs8_71081100": 10000,
        "hs8_71081210": 14034528,
        "hs8_71081310": 6130000,
        "hs8_71090000": 0,
        "hs8_71101100": -9882412,
        "hs8_71101900": 0,
        "hs8_71102100": 0,
        "hs8_71102900": 217306,
        "hs8_71103100": 0,
        "hs8_71103900": 0,
        "hs8_71104100": 0,
        "hs8_71104900": 0,
        "hs8_71110000": 0,
        "hs8_71129201": -618153,
        "hs8_71131110": -78023,
        "hs8_71131120": -87215,
        "hs8_71131150": -17182788,
        "hs8_71131910": -163257,
        "hs8_71131921": 2648213,
        "hs8_71131925": -663926,
        "hs8_71131929": -15215940,
        "hs8_71131930": -80321,
        "hs8_71131950": -70044480,
        "hs8_71132050": -83327,
        "hs8_71141110": 1550000,
        "hs8_71141120": 0,
        "hs8_71141150": -32316,
        "hs8_71141160": -8209,
        "hs8_71141170": -205006,
        "hs8_71142000": -6053,
        "hs8_71151000": 0,
        "hs8_71159005": -10261441,
        "hs8_71159060": -2464,
        "hs8_71161025": -28875,
        "hs8_71162005": -2028649,
        "hs8_71162015": -203506,
        "hs8_71162030": -20672,
        "hs8_71162035": -39907,
        "hs8_71162040": -73133,
        "hs8_71162050": -2015738,
        "hs8_71171100": 10000,
        "hs8_71171905": -9949,
        "hs8_71171915": -38818,
        "hs8_71171920": -4190,
        "hs8_71171930": -11111,
        "hs8_71171990": 1281613,
        "hs8_71179010": 750000,
        "hs8_71179020": -18235,
        "hs8_71179030": -12659,
        "hs8_71179075": -235935,
        "hs8_71179090": 8034939,
        "hs8_71181000": 123111,
        "hs8_71189000": 292202
      }
    ]
  }
}
